Workbook
Name Slicer_Years__Month_Start: #N/A

Sheet swiggy_order_items
A1: order_id | B1: order_items.name | C1: order_items.is_veg | D1: order_items.quantity | E1: Category
A2: 175244332362622 | B2: Michel (Chicken & Mozza Sandwich) | C2: 0 | D2: 1 | E2: =IF(C2=0,"Non_Veg","Veg") -> Non_Veg
A3: 175167017704058 | B3: Supreme Boneless Chicken Biryani | C3: 0 | D3: 1 | E3: =IF(C3=0,"Non_Veg","Veg") -> Non_Veg
A4: 175167017704058 | B4: Mutton Bone Soup | C4: 0 | D4: 1 | E4: =IF(C4=0,"Non_Veg","Veg") -> Non_Veg
A5: 175017114796029 | B5: Mississippi Mud Pie | C5: 0 | D5: 1 | E5: =IF(C5=0,"Non_Veg","Veg") -> Non_Veg
A6: 175017114796029 | B6: Apple Crumble Pie | C6: 1 | D6: 1 | E6: =IF(C6=0,"Non_Veg","Veg") -> Veg
A7: 174973046023416 | B7: Dark Chocolate Smoothie Bowl. | C7: 1 | D7: 1 | E7: =IF(C7=0,"Non_Veg","Veg") -> Veg
A8: 174973046023416 | B8: Banana Peanutbutter Overnight Oats [350kcals][20gm protein] | C8: 1 | D8: 1 | E8: =IF(C8=0,"Non_Veg","Veg") -> Veg
A9: 174906705849277 | B9: Chicken Kheema Lasagne | C9: 0 | D9: 1 | E9: =IF(C9=0,"Non_Veg","Veg") -> Non_Veg
A10: 174906705849277 | B10: Corn & Pepper Lasagne | C10: 1 | D10: 1 | E10: =IF(C10=0,"Non_Veg","Veg") -> Veg
A11: 174329455765789 | B11: Veg. Ramyun | C11: 1 | D11: 1 | E11: =IF(C11=0,"Non_Veg","Veg") -> Veg
A12: 174329455765789 | B12: Chicken Katsu Ramyun | C12: 0 | D12: 1 | E12: =IF(C12=0,"Non_Veg","Veg") -> Non_Veg
A13: 174318296922309 | B13: Onion Rings | C13: 1 | D13: 1 | E13: =IF(C13=0,"Non_Veg","Veg") -> Veg
... A171: 171863054117 | B171: Open Butter Masala Dosa | C171: 1 | D171: 1 | E171: =IF(C171=0,"Non_Veg","Veg") -> Veg

Sheet Sheet1
B3: What % of the orders coupons were applied? (HW)
B5: What % of the orders were delivered during rain? (HW)
B7: All the above metrics at a restaurant and area area level (HW)

Sheet swiggy_orders
A1: order_id | B1: name of the food | C1: veg or non_veg | D1: is_coupon_applied | E1: coupon_applied | F1: Discount _amount | G1: offers_data | H1: order_time | I1: confirmed_time | J1: customer_id | K1: order_status | L1: delivery_boy.name | M1: restaurant_id | N1: restaurant_name | O1: restaurant_address | P1: restaurant_locality | Q1: restaurant_city_name | R1: delivery_time_in_seconds | S1: delivery time hrs | T1: order_total | U1: order_total_with_tip | V1: net_total | W1: item_total | X1: free_delivery_discount_hit | Y1: restaurant_lat_lng | Z1: Distance group | AA1: restaurant_customer_distance | AB1: order_payment_method | AC1: restaurant_area_name | AD1: on_time | AE1: rain_mode | AF1: Month Start | AG1: Area Name | AH1: Restaurant Name | AI1: Latitiude | AJ1: Longitude
A2: 175244332362622 | B2: =_xlfn.XLOOKUP(Table2[[#This Row],[order_id]],swiggy_order_items!A2:A171,swiggy_order_items!B2:B171) -> Michel (Chicken & Mozza Sandwich) | C2: =_xlfn.XLOOKUP(Table2[[#This Row],[name of the food]],swiggy_order_items!B2:B171,swiggy_order_items!E2:E171) -> Non_Veg | D2: TRUE | E2: SWIGGYIT | F2: =IFERROR(TRUNC((_xlfn.TEXTBEFORE(_xlfn.TEXTAFTER(G2,"""total_offer_discount"":"),",")),2),"NO OFFER") -> 120 | G2: [{"id":"7740ff94-cc8f-41cf-b6ec-d4c97cbd0060","super_type":"SUPERTYPE_UNSPECIFIED","total_offer_discount":120,"discount_share":{"swiggy_discount":67.2,"store_discount":52.8,"alliance_discount":0},"discount_type":"PERCENTAGE","description":"60% off","fixed_charges":{"gp":{"id":"","final_price":0}}}] | H2: 2024-05-21 12:28:52 | I2: 2024-05-21 12:29:13 | J2: 21191609 | K2: Delivered | L2: NARREDDY NAGESWARA REDDY | M2: 434304 | N2: Paris Panini - Gourmet Sandwiches & Wraps | O2: No.690/A, 14th Main, 100ft Road, JP Nagar 2nd Phase, Bangalore 560078. | P2: JP Nagar | Q2: Bangalore | R2: 1587 | S2: =Table2[[#This Row],[delivery_time_in_seconds]]/60 -> 26.45 | T2: 146 | U2: 146 | V2: 146 | W2: 225 | X2: 43 | Y2: 12.90649867,77.59165435 | Z2: =IF(Table2[[#This Row],[restaurant_customer_distance]]<=2,"0-2 Km",IF(Table2[[#This Row],[restaurant_customer_distance]]<=5,"2-5 Km",IF(Table2[[#This Row],[restaurant_customer_distance]]<=8,"5-8 Km","8+Km"))) -> 2-5 Km | AA2: 2.2 | AB2: UPICollect | AC2: JP Nagar | AD2: FALSE | AE2: 0 | AF2: =EOMONTH(H2,-1)+1 -> 45413 | AG2: =IFERROR(VLOOKUP(AC2,#REF!,2,0),AC2) -> JP Nagar | AH2: =IFERROR(TRIM(_xlfn.TEXTBEFORE(N2,"-")),N2) -> Paris Panini | AI2: =_xlfn.TEXTBEFORE(Y2,",") -> 12.90649867 | AJ2: =_xlfn.TEXTAFTER(Y2,",") -> 77.59165435
A3: 175167017704058 | B3: =_xlfn.XLOOKUP(Table2[[#This Row],[order_id]],swiggy_order_items!A3:A172,swiggy_order_items!B3:B172) -> Supreme Boneless Chicken Biryani | C3: =_xlfn.XLOOKUP(Table2[[#This Row],[name of the food]],swiggy_order_items!B3:B172,swiggy_order_items!E3:E172) -> Non_Veg | D3: FALSE | E3: No coupon | F3: =IFERROR(TRUNC((_xlfn.TEXTBEFORE(_xlfn.TEXTAFTER(G3,"""total_offer_discount"":"),",")),2),"NO OFFER") -> NO OFFER | G3: "total_offer_discount":NO OFFER, | H3: 2024-05-20 15:00:17 | I3: 2024-05-20 15:00:38 | J3: 21191609 | K3: Delivered | L3: Kesavamoorthi | M3: 12804 | N3: Nandhana Palace | O3: JP nagar, 147, 24th Main Rd, R.K Colony, Marenahalli, 2nd Phase, J. P. Nagar, Bengaluru, Karnataka 560078 | P3: JP Nagar | Q3: Bangalore | R3: 1853 | S3: =Table2[[#This Row],[delivery_time_in_seconds]]/60 -> 30.883333 | T3: 555 | U3: 555 | V3: 555 | W3: 480 | X3: 41 | Y3: 12.914599,77.585509 | Z3: =IF(Table2[[#This Row],[restaurant_customer_distance]]<=2,"0-2 Km",IF(Table2[[#This Row],[restaurant_customer_distance]]<=5,"2-5 Km",IF(Table2[[#This Row],[restaurant_customer_distance]]<=8,"5-8 Km","8+Km"))) -> 2-5 Km | AA3: 2.2 | AB3: UPICollect | AC3: JP Nagar | AD3: FALSE | AE3: 0 | AF3: =EOMONTH(H3,-1)+1 -> 45413 | AG3: =IFERROR(VLOOKUP(AC3,#REF!,2,0),AC3) -> JP Nagar | AH3: =IFERROR(TRIM(_xlfn.TEXTBEFORE(N3,"-")),N3) -> Nandhana Palace | AI3: =_xlfn.TEXTBEFORE(Y3,",") -> 12.914599 | AJ3: =_xlfn.TEXTAFTER(Y3,",") -> 77.585509
A4: 175017114796029 | B4: =_xlfn.XLOOKUP(Table2[[#This Row],[order_id]],swiggy_order_items!A4:A173,swiggy_order_items!B4:B173) -> Mississippi Mud Pie | C4: =_xlfn.XLOOKUP(Table2[[#This Row],[name of the food]],swiggy_order_items!B4:B173,swiggy_order_items!E4:E173) -> Non_Veg | D4: TRUE | E4: MISSEDYOU | F4: =IFERROR(TRUNC((_xlfn.TEXTBEFORE(_xlfn.TEXTAFTER(G4,"""total_offer_discount"":"),",")),2),"NO OFFER") -> 80 | G4: [{"id":"c1399a7d-65f4-486a-ba3e-72a9d9c70cad","super_type":"SUPERTYPE_UNSPECIFIED","total_offer_discount":80,"discount_share":{"swiggy_discount":16,"store_discount":64,"alliance_discount":0},"discount_type":"PERCENTAGE","description":"40% off","fixed_charges":{"gp":{"id":"","final_price":0}}}] | H4: 2024-05-18 21:21:54 | I4: 2024-05-18 21:22:15 | J4: 21191609 | K4: Delivered | L4: Safiul Ansari | M4: 15250 | N4: The Ganache Factory - Cakes & Desserts | O4: #156, 43rd Cross, 8th Block, Next to Udupi Hub Resto, Jayanagar, Bangalore | P4: 8th Block | Q4: Bangalore | R4: 1559 | S4: =Table2[[#This Row],[delivery_time_in_seconds]]/60 -> 25.983333 | T4: 382 | U4: 382 | V4: 382 | W4: 400 | X4: 69 | Y4: 12.91835714,77.578127 | Z4: =IF(Table2[[#This Row],[restaurant_customer_distance]]<=2,"0-2 Km",IF(Table2[[#This Row],[restaurant_customer_distance]]<=5,"2-5 Km",IF(Table2[[#This Row],[restaurant_customer_distance]]<=8,"5-8 Km","8+Km"))) -> 2-5 Km | AA4: 3.6 | AB4: UPICollect | AC4: Jayanagar | AD4: TRUE | AE4: 0 | AF4: =EOMONTH(H4,-1)+1 -> 45413 | AG4: =IFERROR(VLOOKUP(AC4,#REF!,2,0),AC4) -> Jayanagar | AH4: =IFERROR(TRIM(_xlfn.TEXTBEFORE(N4,"-")),N4) -> The Ganache Factory | AI4: =_xlfn.TEXTBEFORE(Y4,",") -> 12.91835714 | AJ4: =_xlfn.TEXTAFTER(Y4,",") -> 77.578127
A5: 174973046023416 | B5: =_xlfn.XLOOKUP(Table2[[#This Row],[order_id]],swiggy_order_items!A5:A174,swiggy_order_items!B5:B174) -> Dark Chocolate Smoothie Bowl. | C5: =_xlfn.XLOOKUP(Table2[[#This Row],[name of the food]],swiggy_order_items!B5:B174,swiggy_order_items!E5:E174) -> Veg | D5: TRUE | E5: SWIGGYIT | F5: =IFERROR(TRUNC((_xlfn.TEXTBEFORE(_xlfn.TEXTAFTER(G5,"""total_offer_discount"":"),",")),2),"NO OFFER") -> 39.99 | G5: [{"id":"28bf3ebb-4a69-4a92-88a4-f491a5f86e17","super_type":"SUPERTYPE_UNSPECIFIED","total_offer_discount":39.99,"discount_share":{"swiggy_discount":0,"store_discount":39.99,"alliance_discount":0},"discount_type":"PERCENTAGE","description":"10% off","fixed_charges":{"gp":{"id":"","final_price":0}}}] | H5: 2024-05-18 09:07:26 | I5: 2024-05-18 09:07:44 | J5: 21191609 | K5: Delivered | L5: Rama Krishna | M5: 630473 | N5: Rasayan | O5: 652,13th cross,29th main road BTM 2nd stage,560078, Bangalore Karnataka | P5: Health Bar | Q5: Bangalore | R5: 3760 | S5: =Table2[[#This Row],[delivery_time_in_seconds]]/60 -> 62.666667 | T5: 421 | U5: 421 | V5: 421 | W5: 415 | X5: 46 | Y5: 12.907799,77.613487 | Z5: =IF(Table2[[#This Row],[restaurant_customer_distance]]<=2,"0-2 Km",IF(Table2[[#This Row],[restaurant_customer_distance]]<=5,"2-5 Km",IF(Table2[[#This Row],[restaurant_customer_distance]]<=8,"5-8 Km","8+Km"))) -> 2-5 Km | AA5: 2.5 | AB5: UPICollect | AC5: BTM 2nd Stage | AD5: FALSE | AE5: 0 | AF5: =EOMONTH(H5,-1)+1 -> 45413 | AG5: =IFERROR(VLOOKUP(AC5,#REF!,2,0),AC5) -> BTM 2nd Stage | AH5: =IFERROR(TRIM(_xlfn.TEXTBEFORE(N5,"-")),N5) -> Rasayan | AI5: =_xlfn.TEXTBEFORE(Y5,",") -> 12.907799 | AJ5: =_xlfn.TEXTAFTER(Y5,",") -> 77.613487
A6: 174906705849277 | B6: =_xlfn.XLOOKUP(Table2[[#This Row],[order_id]],swiggy_order_items!A6:A175,swiggy_order_items!B6:B175) -> Chicken Kheema Lasagne | C6: =_xlfn.XLOOKUP(Table2[[#This Row],[name of the food]],swiggy_order_items!B6:B175,swiggy_order_items!E6:E175) -> Non_Veg | D6: TRUE | E6: DEALICIOUS | F6: =IFERROR(TRUNC((_xlfn.TEXTBEFORE(_xlfn.TEXTAFTER(G6,"""total_offer_discount"":"),",")),2),"NO OFFER") -> 124.99 | G6: [{"id":"91e6269d-640b-443e-a7d4-46089c0574f6","super_type":"SUPERTYPE_UNSPECIFIED","total_offer_discount":124.99,"discount_share":{"swiggy_discount":0,"store_discount":124.99,"alliance_discount":0},"discount_type":"FLAT","description":"FLAT125 off","fixed_charges":{"gp":{"id":"","final_price":0}}}] | H6: 2024-05-17 14:41:45 | I6: 2024-05-17 14:42:09 | J6: 21191609 | K6: Delivered | L6: Tapan Nayak | M6: 34363 | N6: Firangi Bake | O6: Shop No.4, Frist Floor, NGK Complex, Tavarekere Main Rd, 1st Stage, BTM Layout, Bengaluru, Karnataka 560029 ( Above DMart Ready) | P6: NGK Complex | Q6: Bangalore | R6: 2257 | S6: =Table2[[#This Row],[delivery_time_in_seconds]]/60 -> 37.616667 | T6: 556 | U6: 556 | V6: 556 | W6: 624 | X6: 35 | Y6: 12.920219,77.610520 | Z6: =IF(Table2[[#This Row],[restaurant_customer_distance]]<=2,"0-2 Km",IF(Table2[[#This Row],[restaurant_customer_distance]]<=5,"2-5 Km",IF(Table2[[#This Row],[restaurant_customer_distance]]<=8,"5-8 Km","8+Km"))) -> 2-5 Km | AA6: 2.2 | AB6: UPICollect | AC6: BTM 1st Stage | AD6: FALSE | AE6: 0 | AF6: =EOMONTH(H6,-1)+1 -> 45413 | AG6: =IFERROR(VLOOKUP(AC6,#REF!,2,0),AC6) -> BTM 1st Stage | AH6: =IFERROR(TRIM(_xlfn.TEXTBEFORE(N6,"-")),N6) -> Firangi Bake | AI6: =_xlfn.TEXTBEFORE(Y6,",") -> 12.920219 | AJ6: =_xlfn.TEXTAFTER(Y6,",") -> 77.610520
A7: 174329455765789 | B7: =_xlfn.XLOOKUP(Table2[[#This Row],[order_id]],swiggy_order_items!A7:A176,swiggy_order_items!B7:B176) -> Veg. Ramyun | C7: =_xlfn.XLOOKUP(Table2[[#This Row],[name of the food]],swiggy_order_items!B7:B176,swiggy_order_items!E7:E176) -> Veg | D7: TRUE | E7: MDM150 | F7: =IFERROR(TRUNC((_xlfn.TEXTBEFORE(_xlfn.TEXTAFTER(G7,"""total_offer_discount"":"),",")),2),"NO OFFER") -> 149.99 | G7: [{"id":"60d51c5f-a27d-407c-9d72-c55f498dea78","super_type":"SUPERTYPE_UNSPECIFIED","total_offer_discount":149.99,"discount_share":{"swiggy_discount":15,"store_discount":134.99,"alliance_discount":0},"discount_type":"FLAT","description":"Flat ₹150 off","fixed_charges":{"gp":{"id":"","final_price":0}}}] | H7: 2024-05-10 22:20:55 | I7: 2024-05-10 22:21:01 | J7: 21191609 | K7: Delivered | L7: ARUN DYAVANAKATTI | M7: 474244 | N7: Daily Sushi | O7: No.5, 1st Floor, 9th Main Road, 5th block, Jayanagar, 560041 | P7: 5th Block | Q7: Bangalore | R7: 3262 | S7: =Table2[[#This Row],[delivery_time_in_seconds]]/60 -> 54.366667 | T7: 1062 | U7: 1062 | V7: 1062 | W7: 1050 | X7: 45 | Y7: 12.92243257,77.58390586 | Z7: =IF(Table2[[#This Row],[restaurant_customer_distance]]<=2,"0-2 Km",IF(Table2[[#This Row],[restaurant_customer_distance]]<=5,"2-5 Km",IF(Table2[[#This Row],[restaurant_customer_distance]]<=8,"5-8 Km","8+Km"))) -> 2-5 Km | AA7: 3.2 | AB7: Cash | AC7: Jayanagar | AD7: FALSE | AE7: 0 | AF7: =EOMONTH(H7,-1)+1 -> 45413 | AG7: =IFERROR(VLOOKUP(AC7,#REF!,2,0),AC7) -> Jayanagar | AH7: =IFERROR(TRIM(_xlfn.TEXTBEFORE(N7,"-")),N7) -> Daily Sushi | AI7: =_xlfn.TEXTBEFORE(Y7,",") -> 12.92243257 | AJ7: =_xlfn.TEXTAFTER(Y7,",") -> 77.58390586
A8: 174318296922309 | B8: =_xlfn.XLOOKUP(Table2[[#This Row],[order_id]],swiggy_order_items!A8:A177,swiggy_order_items!B8:B177) -> Onion Rings | C8: =_xlfn.XLOOKUP(Table2[[#This Row],[name of the food]],swiggy_order_items!B8:B177,swiggy_order_items!E8:E177) -> Veg | D8: TRUE | E8: SWIGGYIT | F8: =IFERROR(TRUNC((_xlfn.TEXTBEFORE(_xlfn.TEXTAFTER(G8,"""total_offer_discount"":"),",")),2),"NO OFFER") -> 120 | G8: [{"id":"7740ff94-cc8f-41cf-b6ec-d4c97cbd0060","super_type":"SUPERTYPE_UNSPECIFIED","total_offer_discount":120,"discount_share":{"swiggy_discount":67.2,"store_discount":52.8,"alliance_discount":0},"discount_type":"PERCENTAGE","description":"60% off","fixed_charges":{"gp":{"id":"","final_price":0}}}] | H8: 2024-05-10 19:14:56 | I8: 2024-05-10 19:15:01 | J8: 21191609 | K8: Delivered | L8: PARASH | M8: 434304 | N8: Paris Panini - Gourmet Sandwiches & Wraps | O8: No.690/A, 14th Main, 100ft Road, JP Nagar 2nd Phase, Bangalore 560078. | P8: JP Nagar | Q8: Bangalore | R8: 2401 | S8: =Table2[[#This Row],[delivery_time_in_seconds]]/60 -> 40.016667 | T8: 440 | U8: 440 | V8: 440 | W8: 480 | X8: 45 | Y8: 12.90649867,77.59165435 | Z8: =IF(Table2[[#This Row],[restaurant_customer_distance]]<=2,"0-2 Km",IF(Table2[[#This Row],[restaurant_customer_distance]]<=5,"2-5 Km",IF(Table2[[#This Row],[restaurant_customer_distance]]<=8,"5-8 Km","8+Km"))) -> 2-5 Km | AA8: 2.1 | AB8: Cash | AC8: JP Nagar | AD8: FALSE | AE8: 0 | AF8: =EOMONTH(H8,-1)+1 -> 45413 | AG8: =IFERROR(VLOOKUP(AC8,#REF!,2,0),AC8) -> JP Nagar | AH8: =IFERROR(TRIM(_xlfn.TEXTBEFORE(N8,"-")),N8) -> Paris Panini | AI8: =_xlfn.TEXTBEFORE(Y8,",") -> 12.90649867 | AJ8: =_xlfn.TEXTAFTER(Y8,",") -> 77.59165435
A9: 174118005152904 | B9: =_xlfn.XLOOKUP(Table2[[#This Row],[order_id]],swiggy_order_items!A9:A178,swiggy_order_items!B9:B178) -> Special Pandi Curry Thali | C9: =_xlfn.XLOOKUP(Table2[[#This Row],[name of the food]],swiggy_order_items!B9:B178,swiggy_order_items!E9:E178) -> Non_Veg | D9: TRUE | E9: SWIGGYIT | F9: =IFERROR(TRUNC((_xlfn.TEXTBEFORE(_xlfn.TEXTAFTER(G9,"""total_offer_discount"":"),",")),2),"NO OFFER") -> 35 | G9: [{"id":"8a02a1ac-9efe-46ea-9649-fc635c7c8618","super_type":"SUPERTYPE_UNSPECIFIED","total_offer_discount":35,"discount_share":{"swiggy_discount":0,"store_discount":35,"alliance_discount":0},"discount_type":"PERCENTAGE","description":"10% off","fixed_charges":{"gp":{"id":"","final_price":0}}}] | H9: 2024-05-08 11:36:45 | I9: 2024-05-08 11:37:28 | J9: 21191609 | K9: Delivered | L9: Sanjay Kumar Mohanty | M9: 534276 | N9: Naalnaad Mane | O9: 16,2ND FLOOR GOWRY'S BUILDING,ABOVE DOMINO'S,SY NO 13 OF AREKERE VILLAGE,BANNERGHATTA,BANGLAORE,jayanagar,B.B.M.PM south, karnataka - 560076 | P9: Mico Layout | Q9: Bangalore | R9: 2824 | S9: =Table2[[#This Row],[delivery_time_in_seconds]]/60 -> 47.066667 | T9: 352 | U9: 352 | V9: 352 | W9: 350 | X9: 36 | Y9: 12.89009167,77.5976944 | Z9: =IF(Table2[[#This Row],[restaurant_customer_distance]]<=2,"0-2 Km",IF(Table2[[#This Row],[restaurant_customer_distance]]<=5,"2-5 Km",IF(Table2[[#This Row],[restaurant_customer_distance]]<=8,"5-8 Km","8+Km"))) -> 2-5 Km | AA9: 3.2 | AB9: UPICollect | AC9: Arekere | AD9: TRUE | AE9: 0 | AF9: =EOMONTH(H9,-1)+1 -> 45413 | AG9: =IFERROR(VLOOKUP(AC9,#REF!,2,0),AC9) -> Arekere | AH9: =IFERROR(TRIM(_xlfn.TEXTBEFORE(N9,"-")),N9) -> Naalnaad Mane | AI9: =_xlfn.TEXTBEFORE(Y9,",") -> 12.89009167 | AJ9: =_xlfn.TEXTAFTER(Y9,",") -> 77.5976944
A10: 174075356745024 | B10: =_xlfn.XLOOKUP(Table2[[#This Row],[order_id]],swiggy_order_items!A10:A179,swiggy_order_items!B10:B179) -> Overload Brownie [1 Piece] | C10: =_xlfn.XLOOKUP(Table2[[#This Row],[name of the food]],swiggy_order_items!B10:B179,swiggy_order_items!E10:E179) -> Non_Veg | D10: FALSE | E10: No coupon | F10: =IFERROR(TRUNC((_xlfn.TEXTBEFORE(_xlfn.TEXTAFTER(G10,"""total_offer_discount"":"),",")),2),"NO OFFER") -> NO OFFER | G10: "total_offer_discount":NO OFFER, | H10: 2024-05-07 23:45:56 | I10: 2024-05-07 23:46:17 | J10: 21191609 | K10: Delivered | L10: DIDAR HUSSAIN LASKAR | M10: 524936 | N10: Theobroma | O10: SHOP NO-39,SHABARI ARCADE,14TH MAIN ROAD,OPP MAX SHOWROOM, HSR LAYOUT,BANGALORE-560102, BTM Layout , B.B.M.P South, Karnataka-560102 | P10: 7th Sector | Q10: Bangalore | R10: 2011 | S10: =Table2[[#This Row],[delivery_time_in_seconds]]/60 -> 33.516667 | T10: 644 | U10: 644 | V10: 644 | W10: 275 | X10: 71 | Y10: 12.91135428,77.6380469 | Z10: =IF(Table2[[#This Row],[restaurant_customer_distance]]<=2,"0-2 Km",IF(Table2[[#This Row],[restaurant_customer_distance]]<=5,"2-5 Km",IF(Table2[[#This Row],[restaurant_customer_distance]]<=8,"5-8 Km","8+Km"))) -> 5-8 Km | AA10: 5.2 | AB10: UPICollect | AC10: HSR Layout | AD10: TRUE | AE10: 0 | AF10: =EOMONTH(H10,-1)+1 -> 45413 | AG10: =IFERROR(VLOOKUP(AC10,#REF!,2,0),AC10) -> HSR Layout | AH10: =IFERROR(TRIM(_xlfn.TEXTBEFORE(N10,"-")),N10) -> Theobroma | AI10: =_xlfn.TEXTBEFORE(Y10,",") -> 12.91135428 | AJ10: =_xlfn.TEXTAFTER(Y10,",") -> 77.6380469
A11: 174067299373268 | B11: =_xlfn.XLOOKUP(Table2[[#This Row],[order_id]],swiggy_order_items!A11:A180,swiggy_order_items!B11:B180) -> Chocolate Mousse Cup [100g] | C11: =_xlfn.XLOOKUP(Table2[[#This Row],[name of the food]],swiggy_order_items!B11:B180,swiggy_order_items!E11:E180) -> Veg | D11: FALSE | E11: No coupon | F11: =IFERROR(TRUNC((_xlfn.TEXTBEFORE(_xlfn.TEXTAFTER(G11,"""total_offer_discount"":"),",")),2),"NO OFFER") -> NO OFFER | G11: "total_offer_discount":NO OFFER, | H11: 2024-05-07 21:31:39 | I11: 2024-05-07 21:31:57 | J11: 21191609 | K11: Delivered | L11: Vijayakumar V | M11: 437065 | N11: Theobroma | O11: SHOP NO. 475, GROUND FLOOR, 39TH "C" CROSS, 9TH MAIN, 5THBLOCK, JAYANAGAR,BANGALORE, Jayanagar ,B.B.M.P South, Karnataka,560041 | P11: 5th block | Q11: Bangalore | R11: 1455 | S11: =Table2[[#This Row],[delivery_time_in_seconds]]/60 -> 24.25 | T11: 387 | U11: 387 | V11: 387 | W11: 275 | X11: 0 | Y11: 12.92017647,77.5836421 | Z11: =IF(Table2[[#This Row],[restaurant_customer_distance]]<=2,"0-2 Km",IF(Table2[[#This Row],[restaurant_customer_distance]]<=5,"2-5 Km",IF(Table2[[#This Row],[restaurant_customer_distance]]<=8,"5-8 Km","8+Km"))) -> 2-5 Km | AA11: 3.2 | AB11: UPICollect | AC11: Jayanagar | AD11: TRUE | AE11: 0 | AF11: =EOMONTH(H11,-1)+1 -> 45413 | AG11: =IFERROR(VLOOKUP(AC11,#REF!,2,0),AC11) -> Jayanagar | AH11: =IFERROR(TRIM(_xlfn.TEXTBEFORE(N11,"-")),N11) -> Theobroma | AI11: =_xlfn.TEXTBEFORE(Y11,",") -> 12.92017647 | AJ11: =_xlfn.TEXTAFTER(Y11,",") -> 77.5836421
A12: 174058332503576 | B12: =_xlfn.XLOOKUP(Table2[[#This Row],[order_id]],swiggy_order_items!A12:A181,swiggy_order_items!B12:B181) -> Koli Curry With Ney Kulu/Noolputtu | C12: =_xlfn.XLOOKUP(Table2[[#This Row],[name of the food]],swiggy_order_items!B12:B181,swiggy_order_items!E12:E181) -> Non_Veg | D12: TRUE | E12: SWIGGYIT | F12: =IFERROR(TRUNC((_xlfn.TEXTBEFORE(_xlfn.TEXTAFTER(G12,"""total_offer_discount"":"),",")),2),"NO OFFER") -> 28 | G12: [{"id":"8a02a1ac-9efe-46ea-9649-fc635c7c8618","super_type":"SUPERTYPE_UNSPECIFIED","total_offer_discount":28,"discount_share":{"swiggy_discount":0,"store_discount":28,"alliance_discount":0},"discount_type":"PERCENTAGE","description":"10% off","fixed_charges":{"gp":{"id":"","final_price":0}}}] | H12: 2024-05-07 19:02:12 | I12: 2024-05-07 19:02:53 | J12: 21191609 | K12: Delivered | L12: Gangi Reddy | M12: 534276 | N12: Naalnaad Mane | O12: 16,2ND FLOOR GOWRY'S BUILDING,ABOVE DOMINO'S,SY NO 13 OF AREKERE VILLAGE,BANNERGHATTA,BANGLAORE,jayanagar,B.B.M.PM south, karnataka - 560076 | P12: Mico Layout | Q12: Bangalore | R12: 4292 | S12: =Table2[[#This Row],[delivery_time_in_seconds]]/60 -> 71.533333 | T12: 320 | U12: 320 | V12: 320 | W12: 280 | X12: 0 | Y12: 12.89009167,77.5976944 | Z12: =IF(Table2[[#This Row],[restaurant_customer_distance]]<=2,"0-2 Km",IF(Table2[[#This Row],[restaurant_customer_distance]]<=5,"2-5 Km",IF(Table2[[#This Row],[restaurant_customer_distance]]<=8,"5-8 Km","8+Km"))) -> 2-5 Km | AA12: 3.2 | AB12: UPICollect | AC12: Arekere | AD12: FALSE | AE12: 0 | AF12: =EOMONTH(H12,-1)+1 -> 45413 | AG12: =IFERROR(VLOOKUP(AC12,#REF!,2,0),AC12) -> Arekere | AH12: =IFERROR(TRIM(_xlfn.TEXTBEFORE(N12,"-")),N12) -> Naalnaad Mane | AI12: =_xlfn.TEXTBEFORE(Y12,",") -> 12.89009167 | AJ12: =_xlfn.TEXTAFTER(Y12,",") -> 77.5976944
A13: 174037702433562 | B13: =_xlfn.XLOOKUP(Table2[[#This Row],[order_id]],swiggy_order_items!A13:A182,swiggy_order_items!B13:B182) -> Pepperoni Chicken Tikka lasagna | C13: =_xlfn.XLOOKUP(Table2[[#This Row],[name of the food]],swiggy_order_items!B13:B182,swiggy_order_items!E13:E182) -> Non_Veg | D13: TRUE | E13: TRYNEW | F13: =IFERROR(TRUNC((_xlfn.TEXTBEFORE(_xlfn.TEXTAFTER(G13,"""total_offer_discount"":"),",")),2),"NO OFFER") -> 80 | G13: [{"id":"5c8d9a7d-f899-4dcc-998e-d3e0b2960661","super_type":"SUPERTYPE_UNSPECIFIED","total_offer_discount":80,"discount_share":{"swiggy_discount":0,"store_discount":80,"alliance_discount":0},"discount_type":"PERCENTAGE","description":"40% off","fixed_charges":{"gp":{"id":"","final_price":0}}}] | H13: 2024-05-07 13:18:22 | I13: 2024-05-07 13:18:44 | J13: 21191609 | K13: Delivered | L13: Shiba Kairi | M13: 34363 | N13: Firangi Bake | O13: Shop No.4, Frist Floor, NGK Complex, Tavarekere Main Rd, 1st Stage, BTM Layout, Bengaluru, Karnataka 560029 ( Above DMart Ready) | P13: NGK Complex | Q13: Bangalore | R13: 2730 | S13: =Table2[[#This Row],[delivery_time_in_seconds]]/60 -> 45.5 | T13: 320 | U13: 320 | V13: 320 | W13: 325 | X13: 0 | Y13: 12.920219,77.610520 | Z13: =IF(Table2[[#This Row],[restaurant_customer_distance]]<=2,"0-2 Km",IF(Table2[[#This Row],[restaurant_customer_distance]]<=5,"2-5 Km",IF(Table2[[#This Row],[restaurant_customer_distance]]<=8,"5-8 Km","8+Km"))) -> 2-5 Km | AA13: 2.2 | AB13: UPICollect | AC13: BTM 1st Stage | AD13: FALSE | AE13: 0 | AF13: =EOMONTH(H13,-1)+1 -> 45413 | AG13: =IFERROR(VLOOKUP(AC13,#REF!,2,0),AC13) -> BTM 1st Stage | AH13: =IFERROR(TRIM(_xlfn.TEXTBEFORE(N13,"-")),N13) -> Firangi Bake | AI13: =_xlfn.TEXTBEFORE(Y13,",") -> 12.920219 | AJ13: =_xlfn.TEXTAFTER(Y13,",") -> 77.610520
... A25: 173162395766364 | B25: =_xlfn.XLOOKUP(Table2[[#This Row],[order_id]],swiggy_order_items!A25:A194,swiggy_order_items!B25:B194) -> Banana Peanutbutter Overnight Oats [350kcals][20gm protein] | C25: =_xlfn.XLOOKUP(Table2[[#This Row],[name of the food]],swiggy_order_items!B25:B194,swiggy_order_items!E25:E194) -> Veg | D25: TRUE | E25: JUMBO | F25: =IFERROR(TRUNC((_xlfn.TEXTBEFORE(_xlfn.TEXTAFTER(G25,"""total_offer_discount"":"),",")),2),"NO OFFER") -> 149.99 | G25: [{"id":"7b5f26f9-18b8-4c51-aed1-b1e142eba2ae","super_type":"SUPERTYPE_UNSPECIFIED","total_offer_discount":149.99,"discount_share":{"swiggy_discount":0,"store_discount":149.99,"alliance_discount":0},"discount_type":"PERCENTAGE","description":"30% off","fixed_charges":{"gp":{"id":"","final_price":0}}}] | H25: 2024-04-27 10:09:55 | I25: 2024-04-27 10:10:09 | J25: 21191609 | K25: Delivered | L25: RIYAZ AHMED | M25: 630473 | N25: Rasayan | O25: 652,13th cross,29th main road BTM 2nd stage,560078, Bangalore Karnataka | P25: Health Bar | Q25: Bangalore | R25: 2197 | S25: =Table2[[#This Row],[delivery_time_in_seconds]]/60 -> 36.616667 | T25: 489 | U25: 489 | V25: 489 | W25: 580 | X25: 43 | Y25: 12.907799,77.613487 | Z25: =IF(Table2[[#This Row],[restaurant_customer_distance]]<=2,"0-2 Km",IF(Table2[[#This Row],[restaurant_customer_distance]]<=5,"2-5 Km",IF(Table2[[#This Row],[restaurant_customer_distance]]<=8,"5-8 Km","8+Km"))) -> 2-5 Km | AA25: 2.5 | AB25: UPICollect | AC25: BTM 2nd Stage | AD25: FALSE | AE25: 0 | AF25: =EOMONTH(H25,-1)+1 -> 45383 | AG25: =IFERROR(VLOOKUP(AC25,#REF!,2,0),AC25) -> BTM 2nd Stage | AH25: =IFERROR(TRIM(_xlfn.TEXTBEFORE(N25,"-")),N25) -> Rasayan | AI25: =_xlfn.TEXTBEFORE(Y25,",") -> 12.907799 | AJ25: =_xlfn.TEXTAFTER(Y25,",") -> 77.613487
A26: 173162271836174 | B26: =_xlfn.XLOOKUP(Table2[[#This Row],[order_id]],swiggy_order_items!A26:A195,swiggy_order_items!B26:B195) -> Midnight Acai Delight [320Kcals] [25Gm-45Gm Protein] | C26: =_xlfn.XLOOKUP(Table2[[#This Row],[name of the food]],swiggy_order_items!B26:B195,swiggy_order_items!E26:E195) -> Veg | D26: FALSE | E26: No coupon | F26: =IFERROR(TRUNC((_xlfn.TEXTBEFORE(_xlfn.TEXTAFTER(G26,"""total_offer_discount"":"),",")),2),"NO OFFER") -> NO OFFER | G26: "total_offer_discount":NO OFFER, | H26: 2024-04-27 10:07:51 | I26: 2024-04-27 10:08:09 | J26: 21191609 | K26: cancelled | L26: 0 | M26: 630473 | N26: Rasayan | O26: 652,13th cross,29th main road BTM 2nd stage,560078, Bangalore Karnataka | P26: Health Bar | Q26: Bangalore | R26: 0 | S26: =Table2[[#This Row],[delivery_time_in_seconds]]/60 -> 0 | T26: 646 | U26: 646 | V26: 646 | W26: 580 | X26: 43 | Y26: 12.907799,77.613487 | Z26: =IF(Table2[[#This Row],[restaurant_customer_distance]]<=2,"0-2 Km",IF(Table2[[#This Row],[restaurant_customer_distance]]<=5,"2-5 Km",IF(Table2[[#This Row],[restaurant_customer_distance]]<=8,"5-8 Km","8+Km"))) -> 0-2 Km | AA26: 1.9 | AB26: UPICollect | AC26: BTM 2nd Stage | AD26: FALSE | AE26: 0 | AF26: =EOMONTH(H26,-1)+1 -> 45383 | AG26: =IFERROR(VLOOKUP(AC26,#REF!,2,0),AC26) -> BTM 2nd Stage | AH26: =IFERROR(TRIM(_xlfn.TEXTBEFORE(N26,"-")),N26) -> Rasayan | AI26: =_xlfn.TEXTBEFORE(Y26,",") -> 12.907799 | AJ26: =_xlfn.TEXTAFTER(Y26,",") -> 77.613487
A27: 173021459533483 | B27: =_xlfn.XLOOKUP(Table2[[#This Row],[order_id]],swiggy_order_items!A27:A196,swiggy_order_items!B27:B196) -> Wok Tossed Hakka Noodles | C27: =_xlfn.XLOOKUP(Table2[[#This Row],[name of the food]],swiggy_order_items!B27:B196,swiggy_order_items!E27:E196) -> Non_Veg | D27: TRUE | E27: TRYNEW | F27: =IFERROR(TRUNC((_xlfn.TEXTBEFORE(_xlfn.TEXTAFTER(G27,"""total_offer_discount"":"),",")),2),"NO OFFER") -> 75 | G27: [{"id":"f90d8119-321f-4158-a454-d7576a8e0a65","super_type":"SUPERTYPE_UNSPECIFIED","total_offer_discount":75,"discount_share":{"swiggy_discount":18.75,"store_discount":56.25,"alliance_discount":0},"discount_type":"PERCENTAGE","description":"30% off","fixed_charges":{"gp":{"id":"","final_price":0}}}] | H27: 2024-04-25 19:00:59 | I27: 2024-04-25 19:01:33 | J27: 21191609 | K27: Delivered | L27: RAJESH CHETRY | M27: 260968 | N27: Chowman | O27: SAI DURGA ENCLAVE, KATHA NO 1099, AND NO 833/1, GROUND FLOOR, BELLENDUR VILLAGE, VARTHUR HOBLI, BANGALORE, Mahadevapura , B.B.M.P East, Karnataka-560037 | P27: Sai Durga Enclave | Q27: Bangalore | R27: 1950 | S27: =Table2[[#This Row],[delivery_time_in_seconds]]/60 -> 32.5 | T27: 208 | U27: 208 | V27: 208 | W27: 260 | X27: 40 | Y27: 12.92314229,77.6713331 | Z27: =IF(Table2[[#This Row],[restaurant_customer_distance]]<=2,"0-2 Km",IF(Table2[[#This Row],[restaurant_customer_distance]]<=5,"2-5 Km",IF(Table2[[#This Row],[restaurant_customer_distance]]<=8,"5-8 Km","8+Km"))) -> 2-5 Km | AA27: 3.3 | AB27: UPICollect | AC27: Bellandur | AD27: TRUE | AE27: 0 | AF27: =EOMONTH(H27,-1)+1 -> 45383 | AG27: =IFERROR(VLOOKUP(AC27,#REF!,2,0),AC27) -> Bellandur | AH27: =IFERROR(TRIM(_xlfn.TEXTBEFORE(N27,"-")),N27) -> Chowman | AI27: =_xlfn.TEXTBEFORE(Y27,",") -> 12.92314229 | AJ27: =_xlfn.TEXTAFTER(Y27,",") -> 77.6713331
A28: 172937451496694 | B28: =_xlfn.XLOOKUP(Table2[[#This Row],[order_id]],swiggy_order_items!A28:A197,swiggy_order_items!B28:B197) -> Hugo (Fried Chicken & Mozza Sandwich) | C28: =_xlfn.XLOOKUP(Table2[[#This Row],[name of the food]],swiggy_order_items!B28:B197,swiggy_order_items!E28:E197) -> Non_Veg | D28: TRUE | E28: MISSEDYOU | F28: =IFERROR(TRUNC((_xlfn.TEXTBEFORE(_xlfn.TEXTAFTER(G28,"""total_offer_discount"":"),",")),2),"NO OFFER") -> 100 | G28: [{"id":"12337c67-3996-4380-afdd-b7cf7e3de7a3","super_type":"SUPERTYPE_UNSPECIFIED","total_offer_discount":100,"discount_share":{"swiggy_discount":48,"store_discount":52,"alliance_discount":0},"discount_type":"PERCENTAGE","description":"50% off","fixed_charges":{"gp":{"id":"","final_price":0}}}] | H28: 2024-04-24 19:40:51 | I28: 2024-04-24 19:41:11 | J28: 21191609 | K28: Delivered | L28: K Babu | M28: 742267 | N28: Paris Panini - Gourmet Sandwiches & Wraps | O28: Counter No. 23, 24 & 33, No. 53/2, Doddakannelli Village, Varthur Hobli, Bangalore, Mahadevapura , B.B.M.P East, Karnataka-560038 | P28: Sarjapur Road | Q28: Bangalore | R28: 2384 | S28: =Table2[[#This Row],[delivery_time_in_seconds]]/60 -> 39.733333 | T28: 344 | U28: 344 | V28: 344 | W28: 395 | X28: 61 | Y28: 12.90906249,77.68766132 | Z28: =IF(Table2[[#This Row],[restaurant_customer_distance]]<=2,"0-2 Km",IF(Table2[[#This Row],[restaurant_customer_distance]]<=5,"2-5 Km",IF(Table2[[#This Row],[restaurant_customer_distance]]<=8,"5-8 Km","8+Km"))) -> 5-8 Km | AA28: 5.4 | AB28: UPICollect | AC28: Bellandur Sarjapur | AD28: TRUE | AE28: 0 | AF28: =EOMONTH(H28,-1)+1 -> 45383 | AG28: =IFERROR(VLOOKUP(AC28,#REF!,2,0),AC28) -> Bellandur Sarjapur | AH28: =IFERROR(TRIM(_xlfn.TEXTBEFORE(N28,"-")),N28) -> Paris Panini | AI28: =_xlfn.TEXTBEFORE(Y28,",") -> 12.90906249 | AJ28: =_xlfn.TEXTAFTER(Y28,",") -> 77.68766132
A29: 172865582370674 | B29: =_xlfn.XLOOKUP(Table2[[#This Row],[order_id]],swiggy_order_items!A29:A198,swiggy_order_items!B29:B198) -> Belgian Dark Chocolate Milkshake | C29: =_xlfn.XLOOKUP(Table2[[#This Row],[name of the food]],swiggy_order_items!B29:B198,swiggy_order_items!E29:E198) -> Veg | D29: TRUE | E29: SWIGGYIT | F29: =IFERROR(TRUNC((_xlfn.TEXTBEFORE(_xlfn.TEXTAFTER(G29,"""total_offer_discount"":"),",")),2),"NO OFFER") -> 50 | G29: [{"id":"a95119de-61b8-489b-ad8b-1cf7a5d62a5e","super_type":"SUPERTYPE_UNSPECIFIED","total_offer_discount":50,"discount_share":{"swiggy_discount":15,"store_discount":35,"alliance_discount":0},"discount_type":"PERCENTAGE","description":"20% off","fixed_charges":{"gp":{"id":"","final_price":0}}}] | H29: 2024-04-23 23:43:02 | I29: 2024-04-23 23:43:23 | J29: 21191609 | K29: Delivered | L29: Kapsi Mohammed Tufail | M29: 29349 | N29: Frozen Bottle - Milkshakes, Desserts And Ice Cream | O29: 88, Celler Floor, 17th Cross, 14th main, Sector - 4, HSR, Bangalore | P29: HSR Layout | Q29: Bangalore | R29: 1985 | S29: =Table2[[#This Row],[delivery_time_in_seconds]]/60 -> 33.083333 | T29: 301 | U29: 301 | V29: 301 | W29: 289 | X29: 50 | Y29: 12.91233118,77.63839138 | Z29: =IF(Table2[[#This Row],[restaurant_customer_distance]]<=2,"0-2 Km",IF(Table2[[#This Row],[restaurant_customer_distance]]<=5,"2-5 Km",IF(Table2[[#This Row],[restaurant_customer_distance]]<=8,"5-8 Km","8+Km"))) -> 0-2 Km | AA29: 1.7 | AB29: UPICollect | AC29: HSR Layout | AD29: TRUE | AE29: 0 | AF29: =EOMONTH(H29,-1)+1 -> 45383 | AG29: =IFERROR(VLOOKUP(AC29,#REF!,2,0),AC29) -> HSR Layout | AH29: =IFERROR(TRIM(_xlfn.TEXTBEFORE(N29,"-")),N29) -> Frozen Bottle | AI29: =_xlfn.TEXTBEFORE(Y29,",") -> 12.91233118 | AJ29: =_xlfn.TEXTAFTER(Y29,",") -> 77.63839138
A30: 172849812190412 | B30: =_xlfn.XLOOKUP(Table2[[#This Row],[order_id]],swiggy_order_items!A30:A199,swiggy_order_items!B30:B199) -> Chicken Kheema Lasagne | C30: =_xlfn.XLOOKUP(Table2[[#This Row],[name of the food]],swiggy_order_items!B30:B199,swiggy_order_items!E30:E199) -> Non_Veg | D30: TRUE | E30: TRYNEW | F30: =IFERROR(TRUNC((_xlfn.TEXTBEFORE(_xlfn.TEXTAFTER(G30,"""total_offer_discount"":"),",")),2),"NO OFFER") -> 60 | G30: [{"id":"768dad50-eef1-40d7-bfd4-5327ee71bb5a","super_type":"SUPERTYPE_UNSPECIFIED","total_offer_discount":60,"discount_share":{"swiggy_discount":0,"store_discount":60,"alliance_discount":0},"discount_type":"PERCENTAGE","description":"30% off","fixed_charges":{"gp":{"id":"","final_price":0}}}] | H30: 2024-04-23 19:20:12 | I30: 2024-04-23 19:20:29 | J30: 21191609 | K30: Delivered | L30: ANSHUMAN DAS | M30: 34366 | N30: Firangi Bake | O30: SHOP NO 2318,HSR LAYOUT SECTOR ONE,NEAR NIFT COLLEGE,BANGALORE | P30: Near NIFT College, Sector 1 | Q30: Bangalore | R30: 1375 | S30: =Table2[[#This Row],[delivery_time_in_seconds]]/60 -> 22.916667 | T30: 310 | U30: 310 | V30: 310 | W30: 325 | X30: 35 | Y30: 12.912101,77.65163400000006 | Z30: =IF(Table2[[#This Row],[restaurant_customer_distance]]<=2,"0-2 Km",IF(Table2[[#This Row],[restaurant_customer_distance]]<=5,"2-5 Km",IF(Table2[[#This Row],[restaurant_customer_distance]]<=8,"5-8 Km","8+Km"))) -> 0-2 Km | AA30: 0.8 | AB30: UPICollect | AC30: HSR Layout | AD30: FALSE | AE30: 0 | AF30: =EOMONTH(H30,-1)+1 -> 45383 | AG30: =IFERROR(VLOOKUP(AC30,#REF!,2,0),AC30) -> HSR Layout | AH30: =IFERROR(TRIM(_xlfn.TEXTBEFORE(N30,"-")),N30) -> Firangi Bake | AI30: =_xlfn.TEXTBEFORE(Y30,",") -> 12.912101 | AJ30: =_xlfn.TEXTAFTER(Y30,",") -> 77.65163400000006
A31: 172765721740638 | B31: =_xlfn.XLOOKUP(Table2[[#This Row],[order_id]],swiggy_order_items!A31:A200,swiggy_order_items!B31:B200) -> Chicken Fillet Burger Combo | C31: =_xlfn.XLOOKUP(Table2[[#This Row],[name of the food]],swiggy_order_items!B31:B200,swiggy_order_items!E31:E200) -> Non_Veg | D31: TRUE | E31: MDM150 | F31: =IFERROR(TRUNC((_xlfn.TEXTBEFORE(_xlfn.TEXTAFTER(G31,"""total_offer_discount"":"),",")),2),"NO OFFER") -> 150 | G31: [{"id":"24ecd13d-e27f-4858-9c2a-bdc2b708cce4","super_type":"SUPERTYPE_UNSPECIFIED","total_offer_discount":150,"discount_share":{"swiggy_discount":75,"store_discount":75,"alliance_discount":0},"discount_type":"FLAT","description":"Flat ₹150 off","fixed_charges":{"gp":{"id":"","final_price":0}}}] | H31: 2024-04-22 19:58:41 | I31: 2024-04-22 19:59:12 | J31: 21191609 | K31: Delivered | L31: SUSHIL MANDAL | M31: 17036 | N31: Leon's - Burgers & Wings (Leon Grill) | O31: No.17, Ground Floor, 18th Cross Road, 3rd Sector, HSR Layout, Bangalore. | P31: HSR Layout | Q31: Bangalore | R31: 1703 | S31: =Table2[[#This Row],[delivery_time_in_seconds]]/60 -> 28.383333 | T31: 724 | U31: 724 | V31: 724 | W31: 797.57 | X31: 35 | Y31: 12.91181131,77.64374963 | Z31: =IF(Table2[[#This Row],[restaurant_customer_distance]]<=2,"0-2 Km",IF(Table2[[#This Row],[restaurant_customer_distance]]<=5,"2-5 Km",IF(Table2[[#This Row],[restaurant_customer_distance]]<=8,"5-8 Km","8+Km"))) -> 0-2 Km | AA31: 1.6 | AB31: UPICollect | AC31: HSR Layout | AD31: FALSE | AE31: 0 | AF31: =EOMONTH(H31,-1)+1 -> 45383 | AG31: =IFERROR(VLOOKUP(AC31,#REF!,2,0),AC31) -> HSR Layout | AH31: =IFERROR(TRIM(_xlfn.TEXTBEFORE(N31,"-")),N31) -> Leon's | AI31: =_xlfn.TEXTBEFORE(Y31,",") -> 12.91181131 | AJ31: =_xlfn.TEXTAFTER(Y31,",") -> 77.64374963
A32: 172415621290914 | B32: =_xlfn.XLOOKUP(Table2[[#This Row],[order_id]],swiggy_order_items!A32:A201,swiggy_order_items!B32:B201) -> Single Lamb Cheese Burger | C32: =_xlfn.XLOOKUP(Table2[[#This Row],[name of the food]],swiggy_order_items!B32:B201,swiggy_order_items!E32:E201) -> Non_Veg | D32: TRUE | E32: MDM150 | F32: =IFERROR(TRUNC((_xlfn.TEXTBEFORE(_xlfn.TEXTAFTER(G32,"""total_offer_discount"":"),",")),2),"NO OFFER") -> 150 | G32: [{"id":"8cdbbc6c-7669-489e-b255-421d322ec80f","super_type":"SUPERTYPE_UNSPECIFIED","total_offer_discount":150,"discount_share":{"swiggy_discount":75,"store_discount":75,"alliance_discount":0},"discount_type":"FLAT","description":"Flat ₹150 off","fixed_charges":{"gp":{"id":"","final_price":0}}}] | H32: 2024-04-18 18:43:41 | I32: 2024-04-18 18:44:05 | J32: 21191609 | K32: Delivered | L32: Kundan | M32: 17036 | N32: Leon's - Burgers & Wings (Leon Grill) | O32: No.17, Ground Floor, 18th Cross Road, 3rd Sector, HSR Layout, Bangalore. | P32: HSR Layout | Q32: Bangalore | R32: 1726 | S32: =Table2[[#This Row],[delivery_time_in_seconds]]/60 -> 28.766667 | T32: 252 | U32: 252 | V32: 252 | W32: 349 | X32: 31 | Y32: 12.91181131,77.64374963 | Z32: =IF(Table2[[#This Row],[restaurant_customer_distance]]<=2,"0-2 Km",IF(Table2[[#This Row],[restaurant_customer_distance]]<=5,"2-5 Km",IF(Table2[[#This Row],[restaurant_customer_distance]]<=8,"5-8 Km","8+Km"))) -> 0-2 Km | AA32: 0.9 | AB32: UPICollect | AC32: HSR Layout | AD32: TRUE | AE32: 0 | AF32: =EOMONTH(H32,-1)+1 -> 45383 | AG32: =IFERROR(VLOOKUP(AC32,#REF!,2,0),AC32) -> HSR Layout | AH32: =IFERROR(TRIM(_xlfn.TEXTBEFORE(N32,"-")),N32) -> Leon's | AI32: =_xlfn.TEXTBEFORE(Y32,",") -> 12.91181131 | AJ32: =_xlfn.TEXTAFTER(Y32,",") -> 77.64374963
A33: 171120236353593 | B33: =_xlfn.XLOOKUP(Table2[[#This Row],[order_id]],swiggy_order_items!A33:A202,swiggy_order_items!B33:B202) -> Single Lamb Cheese Burger | C33: =_xlfn.XLOOKUP(Table2[[#This Row],[name of the food]],swiggy_order_items!B33:B202,swiggy_order_items!E33:E202) -> Non_Veg | D33: TRUE | E33: MDM150 | F33: =IFERROR(TRUNC((_xlfn.TEXTBEFORE(_xlfn.TEXTAFTER(G33,"""total_offer_discount"":"),",")),2),"NO OFFER") -> 150 | G33: [{"id":"8cdbbc6c-7669-489e-b255-421d322ec80f","super_type":"SUPERTYPE_UNSPECIFIED","total_offer_discount":150,"discount_share":{"swiggy_discount":75,"store_discount":75,"alliance_discount":0},"discount_type":"FLAT","description":"Flat ₹150 off","fixed_charges":{"gp":{"id":"","final_price":0}}}] | H33: 2024-04-03 18:53:56 | I33: 2024-04-03 18:54:20 | J33: 21191609 | K33: Delivered | L33: chandan K | M33: 17036 | N33: Leon's - Burgers & Wings (Leon Grill) | O33: No.17, Ground Floor, 18th Cross Road, 3rd Sector, HSR Layout, Bangalore. | P33: HSR Layout | Q33: Bangalore | R33: 836 | S33: =Table2[[#This Row],[delivery_time_in_seconds]]/60 -> 13.933333 | T33: 252 | U33: 252 | V33: 252 | W33: 349 | X33: 29 | Y33: 12.91181131,77.64374963 | Z33: =IF(Table2[[#This Row],[restaurant_customer_distance]]<=2,"0-2 Km",IF(Table2[[#This Row],[restaurant_customer_distance]]<=5,"2-5 Km",IF(Table2[[#This Row],[restaurant_customer_distance]]<=8,"5-8 Km","8+Km"))) -> 0-2 Km | AA33: 0.2 | AB33: UPICollect | AC33: HSR Layout | AD33: TRUE | AE33: 0 | AF33: =EOMONTH(H33,-1)+1 -> 45383 | AG33: =IFERROR(VLOOKUP(AC33,#REF!,2,0),AC33) -> HSR Layout | AH33: =IFERROR(TRIM(_xlfn.TEXTBEFORE(N33,"-")),N33) -> Leon's | AI33: =_xlfn.TEXTBEFORE(Y33,",") -> 12.91181131 | AJ33: =_xlfn.TEXTAFTER(Y33,",") -> 77.64374963
A34: 170949181342493 | B34: =_xlfn.XLOOKUP(Table2[[#This Row],[order_id]],swiggy_order_items!A34:A203,swiggy_order_items!B34:B203) -> Single Lamb Cheese Burger | C34: =_xlfn.XLOOKUP(Table2[[#This Row],[name of the food]],swiggy_order_items!B34:B203,swiggy_order_items!E34:E203) -> Non_Veg | D34: TRUE | E34: MDM150 | F34: =IFERROR(TRUNC((_xlfn.TEXTBEFORE(_xlfn.TEXTAFTER(G34,"""total_offer_discount"":"),",")),2),"NO OFFER") -> 150 | G34: [{"id":"8cdbbc6c-7669-489e-b255-421d322ec80f","super_type":"SUPERTYPE_UNSPECIFIED","total_offer_discount":150,"discount_share":{"swiggy_discount":75,"store_discount":75,"alliance_discount":0},"discount_type":"FLAT","description":"Flat ₹150 off","fixed_charges":{"gp":{"id":"","final_price":0}}}] | H34: 2024-04-01 19:23:01 | I34: 2024-04-01 19:23:06 | J34: 21191609 | K34: Delivered | L34: Noor Azam | M34: 17036 | N34: Leon's - Burgers & Wings (Leon Grill) | O34: No.17, Ground Floor, 18th Cross Road, 3rd Sector, HSR Layout, Bangalore. | P34: HSR Layout | Q34: Bangalore | R34: 2224 | S34: =Table2[[#This Row],[delivery_time_in_seconds]]/60 -> 37.066667 | T34: 252 | U34: 252 | V34: 252 | W34: 349 | X34: 34 | Y34: 12.91181131,77.64374963 | Z34: =IF(Table2[[#This Row],[restaurant_customer_distance]]<=2,"0-2 Km",IF(Table2[[#This Row],[restaurant_customer_distance]]<=5,"2-5 Km",IF(Table2[[#This Row],[restaurant_customer_distance]]<=8,"5-8 Km","8+Km"))) -> 0-2 Km | AA34: 1.6 | AB34: Cash | AC34: HSR Layout | AD34: FALSE | AE34: 0 | AF34: =EOMONTH(H34,-1)+1 -> 45383 | AG34: =IFERROR(VLOOKUP(AC34,#REF!,2,0),AC34) -> HSR Layout | AH34: =IFERROR(TRIM(_xlfn.TEXTBEFORE(N34,"-")),N34) -> Leon's | AI34: =_xlfn.TEXTBEFORE(Y34,",") -> 12.91181131 | AJ34: =_xlfn.TEXTAFTER(Y34,",") -> 77.64374963
A35: 170849767634192 | B35: =_xlfn.XLOOKUP(Table2[[#This Row],[order_id]],swiggy_order_items!A35:A204,swiggy_order_items!B35:B204) -> Single Lamb Cheese Burger | C35: =_xlfn.XLOOKUP(Table2[[#This Row],[name of the food]],swiggy_order_items!B35:B204,swiggy_order_items!E35:E204) -> Non_Veg | D35: TRUE | E35: MDM150 | F35: =IFERROR(TRUNC((_xlfn.TEXTBEFORE(_xlfn.TEXTAFTER(G35,"""total_offer_discount"":"),",")),2),"NO OFFER") -> 150 | G35: [{"id":"8cdbbc6c-7669-489e-b255-421d322ec80f","super_type":"SUPERTYPE_UNSPECIFIED","total_offer_discount":150,"discount_share":{"swiggy_discount":75,"store_discount":75,"alliance_discount":0},"discount_type":"FLAT","description":"Flat ₹150 off","fixed_charges":{"gp":{"id":"","final_price":0}}}] | H35: 2024-03-31 15:46:07 | I35: 2024-03-31 15:46:25 | J35: 21191609 | K35: Delivered | L35: Bharath R | M35: 17036 | N35: Leon's - Burgers & Wings (Leon Grill) | O35: No.17, Ground Floor, 18th Cross Road, 3rd Sector, HSR Layout, Bangalore. | P35: HSR Layout | Q35: Bangalore | R35: 854 | S35: =Table2[[#This Row],[delivery_time_in_seconds]]/60 -> 14.233333 | T35: 252 | U35: 252 | V35: 252 | W35: 349 | X35: 30 | Y35: 12.91181131,77.64374963 | Z35: =IF(Table2[[#This Row],[restaurant_customer_distance]]<=2,"0-2 Km",IF(Table2[[#This Row],[restaurant_customer_distance]]<=5,"2-5 Km",IF(Table2[[#This Row],[restaurant_customer_distance]]<=8,"5-8 Km","8+Km"))) -> 0-2 Km | AA35: 1.6 | AB35: UPICollect | AC35: HSR Layout | AD35: TRUE | AE35: 0 | AF35: =EOMONTH(H35,-1)+1 -> 45352 | AG35: =IFERROR(VLOOKUP(AC35,#REF!,2,0),AC35) -> HSR Layout | AH35: =IFERROR(TRIM(_xlfn.TEXTBEFORE(N35,"-")),N35) -> Leon's | AI35: =_xlfn.TEXTBEFORE(Y35,",") -> 12.91181131 | AJ35: =_xlfn.TEXTAFTER(Y35,",") -> 77.64374963
A36: 170326417874188 | B36: =_xlfn.XLOOKUP(Table2[[#This Row],[order_id]],swiggy_order_items!A36:A205,swiggy_order_items!B36:B205) -> Roasted Chicken Strip Sandwich | C36: =_xlfn.XLOOKUP(Table2[[#This Row],[name of the food]],swiggy_order_items!B36:B205,swiggy_order_items!E36:E205) -> Non_Veg | D36: TRUE | E36: SWIGGYIT | F36: =IFERROR(TRUNC((_xlfn.TEXTBEFORE(_xlfn.TEXTAFTER(G36,"""total_offer_discount"":"),",")),2),"NO OFFER") -> 80 | G36: [{"id":"16ef3f62-96d1-48fa-977b-3851da22b190","super_type":"SUPERTYPE_UNSPECIFIED","total_offer_discount":80,"discount_share":{"swiggy_discount":20,"store_discount":60,"alliance_discount":0},"discount_type":"PERCENTAGE","description":"40% off","fixed_charges":{"gp":{"id":"","final_price":0}}}] | H36: 2024-03-25 14:23:37 | I36: 2024-03-25 14:23:54 | J36: 21191609 | K36: Delivered | L36: MAHESH BABU | M36: 2675 | N36: Subway | O36: 36, 3rd Store, 7th Sector, 14th main, HSR Layout | P36: 7th Sector | Q36: Bangalore | R36: 779 | S36: =Table2[[#This Row],[delivery_time_in_seconds]]/60 -> 12.983333 | T36: 252 | U36: 252 | V36: 252 | W36: 300 | X36: 32 | Y36: 12.9118135,77.637958 | Z36: =IF(Table2[[#This Row],[restaurant_customer_distance]]<=2,"0-2 Km",IF(Table2[[#This Row],[restaurant_customer_distance]]<=5,"2-5 Km",IF(Table2[[#This Row],[restaurant_customer_distance]]<=8,"5-8 Km","8+Km"))) -> 0-2 Km | AA36: 0.6 | AB36: UPICollect | AC36: Hsr Layout | AD36: TRUE | AE36: 0 | AF36: =EOMONTH(H36,-1)+1 -> 45352 | AG36: =IFERROR(VLOOKUP(AC36,#REF!,2,0),AC36) -> Hsr Layout | AH36: =IFERROR(TRIM(_xlfn.TEXTBEFORE(N36,"-")),N36) -> Subway | AI36: =_xlfn.TEXTBEFORE(Y36,",") -> 12.9118135 | AJ36: =_xlfn.TEXTAFTER(Y36,",") -> 77.637958
A37: 169997934599848 | B37: =_xlfn.XLOOKUP(Table2[[#This Row],[order_id]],swiggy_order_items!A37:A206,swiggy_order_items!B37:B206) -> Roasted Chicken Strip Sandwich | C37: =_xlfn.XLOOKUP(Table2[[#This Row],[name of the food]],swiggy_order_items!B37:B206,swiggy_order_items!E37:E206) -> Non_Veg | D37: TRUE | E37: FLATDEAL | F37: =IFERROR(TRUNC((_xlfn.TEXTBEFORE(_xlfn.TEXTAFTER(G37,"""total_offer_discount"":"),",")),2),"NO OFFER") -> 99.99 | G37: [{"id":"20f94987-8858-4c7d-bf7b-c2ff8a327fa8","super_type":"SUPERTYPE_UNSPECIFIED","total_offer_discount":99.99,"discount_share":{"swiggy_discount":0,"store_discount":99.99,"alliance_discount":0},"discount_type":"FLAT","description":"FLAT100 off","fixed_charges":{"gp":{"id":"","final_price":0}}}] | H37: 2024-03-21 19:08:54 | I37: 2024-03-21 19:09:08 | J37: 21191609 | K37: Delivered | L37: Kumar P | M37: 2675 | N37: Subway | O37: 36, 3rd Store, 7th Sector, 14th main, HSR Layout | P37: 7th Sector | Q37: Bangalore | R37: 2901 | S37: =Table2[[#This Row],[delivery_time_in_seconds]]/60 -> 48.35 | T37: 596 | U37: 596 | V37: 596 | W37: 649 | X37: 34 | Y37: 12.9118135,77.637958 | Z37: =IF(Table2[[#This Row],[restaurant_customer_distance]]<=2,"0-2 Km",IF(Table2[[#This Row],[restaurant_customer_distance]]<=5,"2-5 Km",IF(Table2[[#This Row],[restaurant_customer_distance]]<=8,"5-8 Km","8+Km"))) -> 0-2 Km | AA37: 1.9 | AB37: UPICollect | AC37: Hsr Layout | AD37: FALSE | AE37: 0 | AF37: =EOMONTH(H37,-1)+1 -> 45352 | AG37: =IFERROR(VLOOKUP(AC37,#REF!,2,0),AC37) -> Hsr Layout | AH37: =IFERROR(TRIM(_xlfn.TEXTBEFORE(N37,"-")),N37) -> Subway | AI37: =_xlfn.TEXTBEFORE(Y37,",") -> 12.9118135 | AJ37: =_xlfn.TEXTAFTER(Y37,",") -> 77.637958
A38: 169054716176265 | B38: =_xlfn.XLOOKUP(Table2[[#This Row],[order_id]],swiggy_order_items!A38:A207,swiggy_order_items!B38:B207) -> Roasted Chicken Strip Sandwich | C38: =_xlfn.XLOOKUP(Table2[[#This Row],[name of the food]],swiggy_order_items!B38:B207,swiggy_order_items!E38:E207) -> Non_Veg | D38: TRUE | E38: SWIGGYIT | F38: =IFERROR(TRUNC((_xlfn.TEXTBEFORE(_xlfn.TEXTAFTER(G38,"""total_offer_discount"":"),",")),2),"NO OFFER") -> 80 | G38: [{"id":"e7373c56-9ba3-49f4-be3d-f75ecf92675e","super_type":"SUPERTYPE_UNSPECIFIED","total_offer_discount":80,"discount_share":{"swiggy_discount":20,"store_discount":60,"alliance_discount":0},"discount_type":"PERCENTAGE","description":"40% off","fixed_charges":{"gp":{"id":"","final_price":0}}}] | H38: 2024-03-10 21:08:36 | I38: 2024-03-10 21:09:03 | J38: 21191609 | K38: Delivered | L38: Subrath Panda | M38: 2675 | N38: Subway | O38: 36, 3rd Store, 7th Sector, 14th main, HSR Layout | P38: 7th Sector | Q38: Bangalore | R38: 4130 | S38: =Table2[[#This Row],[delivery_time_in_seconds]]/60 -> 68.833333 | T38: 251 | U38: 251 | V38: 251 | W38: 300 | X38: 57 | Y38: 12.9118135,77.637958 | Z38: =IF(Table2[[#This Row],[restaurant_customer_distance]]<=2,"0-2 Km",IF(Table2[[#This Row],[restaurant_customer_distance]]<=5,"2-5 Km",IF(Table2[[#This Row],[restaurant_customer_distance]]<=8,"5-8 Km","8+Km"))) -> 0-2 Km | AA38: 1.9 | AB38: UPICollect | AC38: Hsr Layout | AD38: FALSE | AE38: 0 | AF38: =EOMONTH(H38,-1)+1 -> 45352 | AG38: =IFERROR(VLOOKUP(AC38,#REF!,2,0),AC38) -> Hsr Layout | AH38: =IFERROR(TRIM(_xlfn.TEXTBEFORE(N38,"-")),N38) -> Subway | AI38: =_xlfn.TEXTBEFORE(Y38,",") -> 12.9118135 | AJ38: =_xlfn.TEXTAFTER(Y38,",") -> 77.637958
... A56: 165409130967084 | B56: =_xlfn.XLOOKUP(Table2[[#This Row],[order_id]],swiggy_order_items!A56:A225,swiggy_order_items!B56:B225) -> Melted Cheese Chicken Shawarma | C56: =_xlfn.XLOOKUP(Table2[[#This Row],[name of the food]],swiggy_order_items!B56:B225,swiggy_order_items!E56:E225) -> Non_Veg | D56: FALSE | E56: No coupon | F56: =IFERROR(TRUNC((_xlfn.TEXTBEFORE(_xlfn.TEXTAFTER(G56,"""total_offer_discount"":"),",")),2),"NO OFFER") -> NO OFFER | G56: "total_offer_discount":NO OFFER, | H56: 2024-01-28 16:28:50 | I56: 2024-01-28 16:28:56 | J56: 21191609 | K56: Delivered | L56: JAGANNATH MOHANTA | M56: 647582 | N56: Smoky Docky | O56: 130, 17th H Main Rd, KHB Colony, M.I.G, 5th Block, Koramangala, Bengaluru, Karnataka 560095, India | P56: KHB Colony | Q56: Bangalore | R56: 1732 | S56: =Table2[[#This Row],[delivery_time_in_seconds]]/60 -> 28.866667 | T56: 233 | U56: 233 | V56: 233 | W56: 209 | X56: 62 | Y56: 12.934678,77.616812 | Z56: =IF(Table2[[#This Row],[restaurant_customer_distance]]<=2,"0-2 Km",IF(Table2[[#This Row],[restaurant_customer_distance]]<=5,"2-5 Km",IF(Table2[[#This Row],[restaurant_customer_distance]]<=8,"5-8 Km","8+Km"))) -> 5-8 Km | AA56: 5.9 | AB56: Cash | AC56: Koramangala | AD56: TRUE | AE56: 0 | AF56: =EOMONTH(H56,-1)+1 -> 45292 | AG56: =IFERROR(VLOOKUP(AC56,#REF!,2,0),AC56) -> Koramangala | AH56: =IFERROR(TRIM(_xlfn.TEXTBEFORE(N56,"-")),N56) -> Smoky Docky | AI56: =_xlfn.TEXTBEFORE(Y56,",") -> 12.934678 | AJ56: =_xlfn.TEXTAFTER(Y56,",") -> 77.616812
A57: 165341581288776 | B57: =_xlfn.XLOOKUP(Table2[[#This Row],[order_id]],swiggy_order_items!A57:A226,swiggy_order_items!B57:B226) -> Mexican Green Wave Pizza | C57: =_xlfn.XLOOKUP(Table2[[#This Row],[name of the food]],swiggy_order_items!B57:B226,swiggy_order_items!E57:E226) -> Veg | D57: TRUE | E57: SWIGGYIT | F57: =IFERROR(TRUNC((_xlfn.TEXTBEFORE(_xlfn.TEXTAFTER(G57,"""total_offer_discount"":"),",")),2),"NO OFFER") -> 50 | G57: [{"id":"0d0cbd02-407f-4bb6-9c39-91b66ef5c01e","super_type":"SUPERTYPE_UNSPECIFIED","total_offer_discount":50,"discount_share":{"swiggy_discount":0,"store_discount":50,"alliance_discount":0},"discount_type":"PERCENTAGE","description":"20% off","fixed_charges":{"gp":{"id":"","final_price":0}}}] | H57: 2024-01-27 21:43:01 | I57: 2024-01-27 21:43:42 | J57: 21191609 | K57: Delivered | L57: 0 | M57: 23805 | N57: Domino's Pizza | O57: Ground Floor, # 1573, Sector 1(Agara), HSR Layout,,Bangalore - 560102 | P57: 1st Sector | Q57: Bangalore | R57: 1409 | S57: =Table2[[#This Row],[delivery_time_in_seconds]]/60 -> 23.483333 | T57: 599 | U57: 599 | V57: 599 | W57: 578 | X57: 0 | Y57: 12.923037,77.646448 | Z57: =IF(Table2[[#This Row],[restaurant_customer_distance]]<=2,"0-2 Km",IF(Table2[[#This Row],[restaurant_customer_distance]]<=5,"2-5 Km",IF(Table2[[#This Row],[restaurant_customer_distance]]<=8,"5-8 Km","8+Km"))) -> 0-2 Km | AA57: 0 | AB57: UPICollect | AC57: HSR Layout | AD57: FALSE | AE57: 0 | AF57: =EOMONTH(H57,-1)+1 -> 45292 | AG57: =IFERROR(VLOOKUP(AC57,#REF!,2,0),AC57) -> HSR Layout | AH57: =IFERROR(TRIM(_xlfn.TEXTBEFORE(N57,"-")),N57) -> Domino's Pizza | AI57: =_xlfn.TEXTBEFORE(Y57,",") -> 12.923037 | AJ57: =_xlfn.TEXTAFTER(Y57,",") -> 77.646448
A58: 164743294943602 | B58: =_xlfn.XLOOKUP(Table2[[#This Row],[order_id]],swiggy_order_items!A58:A227,swiggy_order_items!B58:B227) -> Naked Nutella Waffle | C58: =_xlfn.XLOOKUP(Table2[[#This Row],[name of the food]],swiggy_order_items!B58:B227,swiggy_order_items!E58:E227) -> Veg | D58: TRUE | E58: TRYNEW | F58: =IFERROR(TRUNC((_xlfn.TEXTBEFORE(_xlfn.TEXTAFTER(G58,"""total_offer_discount"":"),",")),2),"NO OFFER") -> 49.99 | G58: [{"id":"66f89a57-1f02-4c46-a99b-8fc3b891874a","super_type":"SUPERTYPE_UNSPECIFIED","total_offer_discount":49.99,"discount_share":{"swiggy_discount":7.5,"store_discount":42.49,"alliance_discount":0},"discount_type":"PERCENTAGE","description":"20% off","fixed_charges":{"gp":{"id":"","final_price":0}}}] | H58: 2024-01-20 23:31:34 | I58: 2024-01-20 23:31:48 | J58: 21191609 | K58: Delivered | L58: RAVI KUMAR MANDAL | M58: 502673 | N58: The Belgian Waffle Co. | O58: Near VI store, 647, 27th main road, sector 2, sector 5, 1st sector HSR Layout, Bengaluru Karnataka - 560102 | P58: 2nd Sector | Q58: Bangalore | R58: 1413 | S58: =Table2[[#This Row],[delivery_time_in_seconds]]/60 -> 23.55 | T58: 588 | U58: 588 | V58: 588 | W58: 586.67 | X58: 36 | Y58: 12.916097,77.65184 | Z58: =IF(Table2[[#This Row],[restaurant_customer_distance]]<=2,"0-2 Km",IF(Table2[[#This Row],[restaurant_customer_distance]]<=5,"2-5 Km",IF(Table2[[#This Row],[restaurant_customer_distance]]<=8,"5-8 Km","8+Km"))) -> 0-2 Km | AA58: 0.5 | AB58: UPICollect | AC58: HSR Layout | AD58: TRUE | AE58: 0 | AF58: =EOMONTH(H58,-1)+1 -> 45292 | AG58: =IFERROR(VLOOKUP(AC58,#REF!,2,0),AC58) -> HSR Layout | AH58: =IFERROR(TRIM(_xlfn.TEXTBEFORE(N58,"-")),N58) -> The Belgian Waffle Co. | AI58: =_xlfn.TEXTBEFORE(Y58,",") -> 12.916097 | AJ58: =_xlfn.TEXTAFTER(Y58,",") -> 77.65184
A59: 164714296625099 | B59: =_xlfn.XLOOKUP(Table2[[#This Row],[order_id]],swiggy_order_items!A59:A228,swiggy_order_items!B59:B228) -> Melted Cheese Chicken Shawarma | C59: =_xlfn.XLOOKUP(Table2[[#This Row],[name of the food]],swiggy_order_items!B59:B228,swiggy_order_items!E59:E228) -> Non_Veg | D59: FALSE | E59: No coupon | F59: =IFERROR(TRUNC((_xlfn.TEXTBEFORE(_xlfn.TEXTAFTER(G59,"""total_offer_discount"":"),",")),2),"NO OFFER") -> NO OFFER | G59: "total_offer_discount":NO OFFER, | H59: 2024-01-20 15:28:16 | I59: 2024-01-20 15:28:43 | J59: 21191609 | K59: Delivered | L59: Imdadul Hoque Laskar | M59: 647582 | N59: Smoky Docky | O59: 130, 17th H Main Rd, KHB Colony, M.I.G, 5th Block, Koramangala, Bengaluru, Karnataka 560095, India | P59: KHB Colony | Q59: Bangalore | R59: 2746 | S59: =Table2[[#This Row],[delivery_time_in_seconds]]/60 -> 45.766667 | T59: 233 | U59: 233 | V59: 233 | W59: 209 | X59: 58 | Y59: 12.934678,77.616812 | Z59: =IF(Table2[[#This Row],[restaurant_customer_distance]]<=2,"0-2 Km",IF(Table2[[#This Row],[restaurant_customer_distance]]<=5,"2-5 Km",IF(Table2[[#This Row],[restaurant_customer_distance]]<=8,"5-8 Km","8+Km"))) -> 5-8 Km | AA59: 5.9 | AB59: UPICollect | AC59: Koramangala | AD59: FALSE | AE59: 0 | AF59: =EOMONTH(H59,-1)+1 -> 45292 | AG59: =IFERROR(VLOOKUP(AC59,#REF!,2,0),AC59) -> Koramangala | AH59: =IFERROR(TRIM(_xlfn.TEXTBEFORE(N59,"-")),N59) -> Smoky Docky | AI59: =_xlfn.TEXTBEFORE(Y59,",") -> 12.934678 | AJ59: =_xlfn.TEXTAFTER(Y59,",") -> 77.616812
A60: 164376172877898 | B60: =_xlfn.XLOOKUP(Table2[[#This Row],[order_id]],swiggy_order_items!A60:A229,swiggy_order_items!B60:B229) -> Salted Caramel Brownie | C60: =_xlfn.XLOOKUP(Table2[[#This Row],[name of the food]],swiggy_order_items!B60:B229,swiggy_order_items!E60:E229) -> Non_Veg | D60: TRUE | E60: FLAT100 | F60: =IFERROR(TRUNC((_xlfn.TEXTBEFORE(_xlfn.TEXTAFTER(G60,"""total_offer_discount"":"),",")),2),"NO OFFER") -> 99.99 | G60: [{"id":"c5767fa3-4c94-4be2-88d4-9b923f4a2e14","super_type":"SUPERTYPE_UNSPECIFIED","total_offer_discount":99.99,"discount_share":{"swiggy_discount":0,"store_discount":99.99,"alliance_discount":0},"discount_type":"FLAT","description":"Flat ₹100 off","fixed_charges":{"gp":{"id":"","final_price":0}}}] | H60: 2024-01-16 17:32:52 | I60: 2024-01-16 17:33:03 | J60: 21191609 | K60: Delivered | L60: Pravin Kumar | M60: 144115 | N60: The Ganache Factory - Cakes & Desserts | O60: Parcel 5 Food Court, Embassy Tech Village, Outer Ring Road, Near New Horizon College, Devarabeesanahalli, Varthur Hobli, Bangalore , Mahadevapura , B.B.M.P East, Karnataka-560103 | P60: Bellandur Sarjapur | Q60: Bangalore | R60: 2411 | S60: =Table2[[#This Row],[delivery_time_in_seconds]]/60 -> 40.183333 | T60: 886 | U60: 886 | V60: 886 | W60: 913.5 | X60: 78 | Y60: 12.927366,77.692146 | Z60: =IF(Table2[[#This Row],[restaurant_customer_distance]]<=2,"0-2 Km",IF(Table2[[#This Row],[restaurant_customer_distance]]<=5,"2-5 Km",IF(Table2[[#This Row],[restaurant_customer_distance]]<=8,"5-8 Km","8+Km"))) -> 5-8 Km | AA60: 6.2 | AB60: UPICollect | AC60: Devarabeesanahalli | AD60: TRUE | AE60: 0 | AF60: =EOMONTH(H60,-1)+1 -> 45292 | AG60: =IFERROR(VLOOKUP(AC60,#REF!,2,0),AC60) -> Devarabeesanahalli | AH60: =IFERROR(TRIM(_xlfn.TEXTBEFORE(N60,"-")),N60) -> The Ganache Factory | AI60: =_xlfn.TEXTBEFORE(Y60,",") -> 12.927366 | AJ60: =_xlfn.TEXTAFTER(Y60,",") -> 77.692146
A61: 164376027513893 | B61: =_xlfn.XLOOKUP(Table2[[#This Row],[order_id]],swiggy_order_items!A61:A230,swiggy_order_items!B61:B230) -> Nutella Stuffed Chocochips Cookie(1 Pc) | C61: =_xlfn.XLOOKUP(Table2[[#This Row],[name of the food]],swiggy_order_items!B61:B230,swiggy_order_items!E61:E230) -> Non_Veg | D61: TRUE | E61: FLAT100 | F61: =IFERROR(TRUNC((_xlfn.TEXTBEFORE(_xlfn.TEXTAFTER(G61,"""total_offer_discount"":"),",")),2),"NO OFFER") -> 99.99 | G61: [{"id":"4102e284-fde9-40d3-b050-82926746d231","super_type":"SUPERTYPE_UNSPECIFIED","total_offer_discount":99.99,"discount_share":{"swiggy_discount":0,"store_discount":99.99,"alliance_discount":0},"discount_type":"FLAT","description":"Flat ₹100 off","fixed_charges":{"gp":{"id":"","final_price":0}}}] | H61: 2024-01-16 17:30:27 | I61: 2024-01-16 17:30:32 | J61: 21191609 | K61: cancelled | L61: 0 | M61: 15250 | N61: The Ganache Factory - Cakes & Desserts | O61: #156, 43rd Cross, 8th Block, Next to Udupi Hub Resto, Jayanagar, Bangalore | P61: 8th Block | Q61: Bangalore | R61: 0 | S61: =Table2[[#This Row],[delivery_time_in_seconds]]/60 -> 0 | T61: 885 | U61: 885 | V61: 885 | W61: 913.5 | X61: 92 | Y61: 12.91835714,77.578127 | Z61: =IF(Table2[[#This Row],[restaurant_customer_distance]]<=2,"0-2 Km",IF(Table2[[#This Row],[restaurant_customer_distance]]<=5,"2-5 Km",IF(Table2[[#This Row],[restaurant_customer_distance]]<=8,"5-8 Km","8+Km"))) -> 8+Km | AA61: 8.4 | AB61: UPICollect | AC61: Jayanagar | AD61: FALSE | AE61: 0 | AF61: =EOMONTH(H61,-1)+1 -> 45292 | AG61: =IFERROR(VLOOKUP(AC61,#REF!,2,0),AC61) -> Jayanagar | AH61: =IFERROR(TRIM(_xlfn.TEXTBEFORE(N61,"-")),N61) -> The Ganache Factory | AI61: =_xlfn.TEXTBEFORE(Y61,",") -> 12.91835714 | AJ61: =_xlfn.TEXTAFTER(Y61,",") -> 77.578127
A62: 164191765873335 | B62: =_xlfn.XLOOKUP(Table2[[#This Row],[order_id]],swiggy_order_items!A62:A231,swiggy_order_items!B62:B231) -> Chicken Kheema Cheese Paratha | C62: =_xlfn.XLOOKUP(Table2[[#This Row],[name of the food]],swiggy_order_items!B62:B231,swiggy_order_items!E62:E231) -> Non_Veg | D62: TRUE | E62: FLATDEAL | F62: =IFERROR(TRUNC((_xlfn.TEXTBEFORE(_xlfn.TEXTAFTER(G62,"""total_offer_discount"":"),",")),2),"NO OFFER") -> 99.99 | G62: [{"id":"e869bbb4-07f7-44d5-a519-1acaeadf5e53","super_type":"SUPERTYPE_UNSPECIFIED","total_offer_discount":99.99,"discount_share":{"swiggy_discount":29.99,"store_discount":70,"alliance_discount":0},"discount_type":"FLAT","description":"FLAT100 off","fixed_charges":{"gp":{"id":"","final_price":0}}}] | H62: 2024-01-14 14:19:25 | I62: 2024-01-14 14:19:42 | J62: 21191609 | K62: Delivered | L62: Siddartha U | M62: 375045 | N62: Paratha Envy | O62: NO.504, 2ND FLOOR, 6TH CROSS, 6TH BLOCK, KORAMANGALA BANGALORE., BTM Layout, B.B.M.P South, Karnataka-560095 | P62: 6th Block | Q62: Bangalore | R62: 3551 | S62: =Table2[[#This Row],[delivery_time_in_seconds]]/60 -> 59.183333 | T62: 466 | U62: 466 | V62: 466 | W62: 496 | X62: 52 | Y62: 12.937246,77.624643 | Z62: =IF(Table2[[#This Row],[restaurant_customer_distance]]<=2,"0-2 Km",IF(Table2[[#This Row],[restaurant_customer_distance]]<=5,"2-5 Km",IF(Table2[[#This Row],[restaurant_customer_distance]]<=8,"5-8 Km","8+Km"))) -> 5-8 Km | AA62: 5.2 | AB62: UPICollect | AC62: Koramangala | AD62: FALSE | AE62: 0 | AF62: =EOMONTH(H62,-1)+1 -> 45292 | AG62: =IFERROR(VLOOKUP(AC62,#REF!,2,0),AC62) -> Koramangala | AH62: =IFERROR(TRIM(_xlfn.TEXTBEFORE(N62,"-")),N62) -> Paratha Envy | AI62: =_xlfn.TEXTBEFORE(Y62,",") -> 12.937246 | AJ62: =_xlfn.TEXTAFTER(Y62,",") -> 77.624643
A63: 163711888473406 | B63: =_xlfn.XLOOKUP(Table2[[#This Row],[order_id]],swiggy_order_items!A63:A232,swiggy_order_items!B63:B232) -> Big Spicy Paneer Wrap | C63: =_xlfn.XLOOKUP(Table2[[#This Row],[name of the food]],swiggy_order_items!B63:B232,swiggy_order_items!E63:E232) -> Veg | D63: FALSE | E63: No coupon | F63: =IFERROR(TRUNC((_xlfn.TEXTBEFORE(_xlfn.TEXTAFTER(G63,"""total_offer_discount"":"),",")),2),"NO OFFER") -> NO OFFER | G63: "total_offer_discount":NO OFFER, | H63: 2024-01-09 01:01:28 | I63: 2024-01-09 01:01:48 | J63: 21191609 | K63: Delivered | L63: Binoy Debbarma | M63: 23682 | N63: McDonald's | O63: HSR Layout #1, 14th Main,HSR LSector VII, Bengaluru- 56102. | P63: HSR Layout | Q63: Bangalore | R63: 1000 | S63: =Table2[[#This Row],[delivery_time_in_seconds]]/60 -> 16.666667 | T63: 270 | U63: 270 | V63: 270 | W63: 220 | X63: 36 | Y63: 12.91207388,77.6380679 | Z63: =IF(Table2[[#This Row],[restaurant_customer_distance]]<=2,"0-2 Km",IF(Table2[[#This Row],[restaurant_customer_distance]]<=5,"2-5 Km",IF(Table2[[#This Row],[restaurant_customer_distance]]<=8,"5-8 Km","8+Km"))) -> 0-2 Km | AA63: 0.4 | AB63: UPICollect | AC63: HSR Layout | AD63: FALSE | AE63: 0 | AF63: =EOMONTH(H63,-1)+1 -> 45292 | AG63: =IFERROR(VLOOKUP(AC63,#REF!,2,0),AC63) -> HSR Layout | AH63: =IFERROR(TRIM(_xlfn.TEXTBEFORE(N63,"-")),N63) -> McDonald's | AI63: =_xlfn.TEXTBEFORE(Y63,",") -> 12.91207388 | AJ63: =_xlfn.TEXTAFTER(Y63,",") -> 77.6380679
A64: 163004675209983 | B64: =_xlfn.XLOOKUP(Table2[[#This Row],[order_id]],swiggy_order_items!A64:A233,swiggy_order_items!B64:B233) -> Nutella Cheese Cake | C64: =_xlfn.XLOOKUP(Table2[[#This Row],[name of the food]],swiggy_order_items!B64:B233,swiggy_order_items!E64:E233) -> Non_Veg | D64: TRUE | E64: TRYNEW | F64: =IFERROR(TRUNC((_xlfn.TEXTBEFORE(_xlfn.TEXTAFTER(G64,"""total_offer_discount"":"),",")),2),"NO OFFER") -> 35.7 | G64: [{"id":"c5752e1c-f5c2-4414-85fa-57de3a043c19","super_type":"SUPERTYPE_UNSPECIFIED","total_offer_discount":35.7,"discount_share":{"swiggy_discount":0,"store_discount":35.7,"alliance_discount":0},"discount_type":"PERCENTAGE","description":"10% off","fixed_charges":{"gp":{"id":"","final_price":0}}}] | H64: 2023-12-31 20:34:35 | I64: 2023-12-31 20:34:53 | J64: 21191609 | K64: Delivered | L64: SUMANMANDAL | M64: 144115 | N64: The Ganache Factory - Cakes & Desserts | O64: Parcel 5 Food Court, Embassy Tech Village, Outer Ring Road, Near New Horizon College, Devarabeesanahalli, Varthur Hobli, Bangalore , Mahadevapura , B.B.M.P East, Karnataka-560103 | P64: Bellandur Sarjapur | Q64: Bangalore | R64: 2664 | S64: =Table2[[#This Row],[delivery_time_in_seconds]]/60 -> 44.4 | T64: 342 | U64: 342 | V64: 342 | W64: 357 | X64: 76 | Y64: 12.927366,77.692146 | Z64: =IF(Table2[[#This Row],[restaurant_customer_distance]]<=2,"0-2 Km",IF(Table2[[#This Row],[restaurant_customer_distance]]<=5,"2-5 Km",IF(Table2[[#This Row],[restaurant_customer_distance]]<=8,"5-8 Km","8+Km"))) -> 5-8 Km | AA64: 6.2 | AB64: UPICollect | AC64: Devarabeesanahalli | AD64: FALSE | AE64: 0 | AF64: =EOMONTH(H64,-1)+1 -> 45261 | AG64: =IFERROR(VLOOKUP(AC64,#REF!,2,0),AC64) -> Devarabeesanahalli | AH64: =IFERROR(TRIM(_xlfn.TEXTBEFORE(N64,"-")),N64) -> The Ganache Factory | AI64: =_xlfn.TEXTBEFORE(Y64,",") -> 12.927366 | AJ64: =_xlfn.TEXTAFTER(Y64,",") -> 77.692146
A65: 163004361179135 | B65: =_xlfn.XLOOKUP(Table2[[#This Row],[order_id]],swiggy_order_items!A65:A234,swiggy_order_items!B65:B234) -> Veg. Ramyun | C65: =_xlfn.XLOOKUP(Table2[[#This Row],[name of the food]],swiggy_order_items!B65:B234,swiggy_order_items!E65:E234) -> Veg | D65: FALSE | E65: No coupon | F65: =IFERROR(TRUNC((_xlfn.TEXTBEFORE(_xlfn.TEXTAFTER(G65,"""total_offer_discount"":"),",")),2),"NO OFFER") -> NO OFFER | G65: "total_offer_discount":NO OFFER, | H65: 2023-12-31 20:29:21 | I65: 2023-12-31 20:29:27 | J65: 21191609 | K65: Delivered | L65: Mohammad Wasim Akram | M65: 254655 | N65: Daily Sushi | O65: No.1212, SBM Fortune, 4th Floor, 22nd Cross Road, 14th Main Rd, 3rd Sector, HSR Layout, Bengaluru, Karnataka 560102, India | P65: 3rd Sector | Q65: Bangalore | R65: 1889 | S65: =Table2[[#This Row],[delivery_time_in_seconds]]/60 -> 31.483333 | T65: 467 | U65: 467 | V65: 467 | W65: 400 | X65: 31 | Y65: 12.909368,77.638656 | Z65: =IF(Table2[[#This Row],[restaurant_customer_distance]]<=2,"0-2 Km",IF(Table2[[#This Row],[restaurant_customer_distance]]<=5,"2-5 Km",IF(Table2[[#This Row],[restaurant_customer_distance]]<=8,"5-8 Km","8+Km"))) -> 2-5 Km | AA65: 2.1 | AB65: UPICollect | AC65: HSR Layout | AD65: FALSE | AE65: 0 | AF65: =EOMONTH(H65,-1)+1 -> 45261 | AG65: =IFERROR(VLOOKUP(AC65,#REF!,2,0),AC65) -> HSR Layout | AH65: =IFERROR(TRIM(_xlfn.TEXTBEFORE(N65,"-")),N65) -> Daily Sushi | AI65: =_xlfn.TEXTBEFORE(Y65,",") -> 12.909368 | AJ65: =_xlfn.TEXTAFTER(Y65,",") -> 77.638656
A66: 162553743923962 | B66: =_xlfn.XLOOKUP(Table2[[#This Row],[order_id]],swiggy_order_items!A66:A235,swiggy_order_items!B66:B235) -> Trapper Creek (Buff) | C66: =_xlfn.XLOOKUP(Table2[[#This Row],[name of the food]],swiggy_order_items!B66:B235,swiggy_order_items!E66:E235) -> Non_Veg | D66: TRUE | E66: CELEBRATIONS | F66: =IFERROR(TRUNC((_xlfn.TEXTBEFORE(_xlfn.TEXTAFTER(G66,"""total_offer_discount"":"),",")),2),"NO OFFER") -> 174.99 | G66: [{"id":"0cf35ab8-1dc8-4c78-8500-44beda4d0877","super_type":"SUPERTYPE_UNSPECIFIED","total_offer_discount":174.99,"discount_share":{"swiggy_discount":52.5,"store_discount":122.49,"alliance_discount":0},"discount_type":"FLAT","description":"Flat ₹175 off","fixed_charges":{"gp":{"id":"","final_price":0}}}] | H66: 2023-12-26 15:19:03 | I66: 2023-12-26 15:19:25 | J66: 21191609 | K66: Delivered | L66: UMESH | M66: 398360 | N66: Burger Seigneur | O66: #717, 10th main road 2nd cross Hosapalya Opposite of Subodhini English high school ITI layout sector 7. | P66: MANGAMMANAPALYA | Q66: Bangalore | R66: 1788 | S66: =Table2[[#This Row],[delivery_time_in_seconds]]/60 -> 29.8 | T66: 788 | U66: 788 | V66: 788 | W66: 920 | X66: 40 | Y66: 12.90073452,77.6400283 | Z66: =IF(Table2[[#This Row],[restaurant_customer_distance]]<=2,"0-2 Km",IF(Table2[[#This Row],[restaurant_customer_distance]]<=5,"2-5 Km",IF(Table2[[#This Row],[restaurant_customer_distance]]<=8,"5-8 Km","8+Km"))) -> 2-5 Km | AA66: 2.8 | AB66: UPICollect | AC66: ITI layout, Hosapalya | AD66: FALSE | AE66: 0 | AF66: =EOMONTH(H66,-1)+1 -> 45261 | AG66: =IFERROR(VLOOKUP(AC66,#REF!,2,0),AC66) -> ITI layout, Hosapalya | AH66: =IFERROR(TRIM(_xlfn.TEXTBEFORE(N66,"-")),N66) -> Burger Seigneur | AI66: =_xlfn.TEXTBEFORE(Y66,",") -> 12.90073452 | AJ66: =_xlfn.TEXTAFTER(Y66,",") -> 77.6400283
A67: 162461263812077 | B67: =_xlfn.XLOOKUP(Table2[[#This Row],[order_id]],swiggy_order_items!A67:A236,swiggy_order_items!B67:B236) -> Paris Delice (Buff) | C67: =_xlfn.XLOOKUP(Table2[[#This Row],[name of the food]],swiggy_order_items!B67:B236,swiggy_order_items!E67:E236) -> Non_Veg | D67: TRUE | E67: MISSEDYOU | F67: =IFERROR(TRUNC((_xlfn.TEXTBEFORE(_xlfn.TEXTAFTER(G67,"""total_offer_discount"":"),",")),2),"NO OFFER") -> 80 | G67: [{"id":"8493942f-3551-4789-a766-bd2e8eab5603","super_type":"SUPERTYPE_UNSPECIFIED","total_offer_discount":80,"discount_share":{"swiggy_discount":12,"store_discount":68,"alliance_discount":0},"discount_type":"PERCENTAGE","description":"40% off","fixed_charges":{"gp":{"id":"","final_price":0}}}] | H67: 2023-12-25 13:37:43 | I67: 2023-12-25 13:38:02 | J67: 21191609 | K67: Delivered | L67: UNOOSE YUSUF | M67: 398360 | N67: Burger Seigneur | O67: #717, 10th main road 2nd cross Hosapalya Opposite of Subodhini English high school ITI layout sector 7. | P67: MANGAMMANAPALYA | Q67: Bangalore | R67: 1389 | S67: =Table2[[#This Row],[delivery_time_in_seconds]]/60 -> 23.15 | T67: 372 | U67: 372 | V67: 372 | W67: 430 | X67: 40 | Y67: 12.90073452,77.6400283 | Z67: =IF(Table2[[#This Row],[restaurant_customer_distance]]<=2,"0-2 Km",IF(Table2[[#This Row],[restaurant_customer_distance]]<=5,"2-5 Km",IF(Table2[[#This Row],[restaurant_customer_distance]]<=8,"5-8 Km","8+Km"))) -> 2-5 Km | AA67: 2.7 | AB67: UPICollect | AC67: ITI layout, Hosapalya | AD67: TRUE | AE67: 0 | AF67: =EOMONTH(H67,-1)+1 -> 45261 | AG67: =IFERROR(VLOOKUP(AC67,#REF!,2,0),AC67) -> ITI layout, Hosapalya | AH67: =IFERROR(TRIM(_xlfn.TEXTBEFORE(N67,"-")),N67) -> Burger Seigneur | AI67: =_xlfn.TEXTBEFORE(Y67,",") -> 12.90073452 | AJ67: =_xlfn.TEXTAFTER(Y67,",") -> 77.6400283
A68: 161080636531967 | B68: =_xlfn.XLOOKUP(Table2[[#This Row],[order_id]],swiggy_order_items!A68:A237,swiggy_order_items!B68:B237) -> Tandoori Chicken Tikka Cheese Pull Sandwich | C68: =_xlfn.XLOOKUP(Table2[[#This Row],[name of the food]],swiggy_order_items!B68:B237,swiggy_order_items!E68:E237) -> Non_Veg | D68: TRUE | E68: SWIGGYIT | F68: =IFERROR(TRUNC((_xlfn.TEXTBEFORE(_xlfn.TEXTAFTER(G68,"""total_offer_discount"":"),",")),2),"NO OFFER") -> 80 | G68: [{"id":"485642ce-1796-4eab-9811-3ff5e4b7d538","super_type":"SUPERTYPE_UNSPECIFIED","total_offer_discount":80,"discount_share":{"swiggy_discount":28,"store_discount":52,"alliance_discount":0},"discount_type":"PERCENTAGE","description":"40% off","fixed_charges":{"gp":{"id":"","final_price":0}}}] | H68: 2023-12-09 14:07:16 | I68: 2023-12-09 14:07:34 | J68: 21191609 | K68: Delivered | L68: Irfanirfu | M68: 2675 | N68: Subway | O68: 36, 3rd Store, 7th Sector, 14th main, HSR Layout | P68: 7th Sector | Q68: Bangalore | R68: 1080 | S68: =Table2[[#This Row],[delivery_time_in_seconds]]/60 -> 18 | T68: 355 | U68: 355 | V68: 355 | W68: 399 | X68: 33 | Y68: 12.9118135,77.637958 | Z68: =IF(Table2[[#This Row],[restaurant_customer_distance]]<=2,"0-2 Km",IF(Table2[[#This Row],[restaurant_customer_distance]]<=5,"2-5 Km",IF(Table2[[#This Row],[restaurant_customer_distance]]<=8,"5-8 Km","8+Km"))) -> 0-2 Km | AA68: 1.9 | AB68: UPICollect | AC68: Hsr Layout | AD68: TRUE | AE68: 0 | AF68: =EOMONTH(H68,-1)+1 -> 45261 | AG68: =IFERROR(VLOOKUP(AC68,#REF!,2,0),AC68) -> Hsr Layout | AH68: =IFERROR(TRIM(_xlfn.TEXTBEFORE(N68,"-")),N68) -> Subway | AI68: =_xlfn.TEXTBEFORE(Y68,",") -> 12.9118135 | AJ68: =_xlfn.TEXTAFTER(Y68,",") -> 77.637958
A69: 160474594456670 | B69: =_xlfn.XLOOKUP(Table2[[#This Row],[order_id]],swiggy_order_items!A69:A238,swiggy_order_items!B69:B238) -> Spicy Chick'n Cheese | C69: =_xlfn.XLOOKUP(Table2[[#This Row],[name of the food]],swiggy_order_items!B69:B238,swiggy_order_items!E69:E238) -> Non_Veg | D69: TRUE | E69: MISSEDYOU | F69: =IFERROR(TRUNC((_xlfn.TEXTBEFORE(_xlfn.TEXTAFTER(G69,"""total_offer_discount"":"),",")),2),"NO OFFER") -> 80 | G69: [{"id":"bf585ef3-1522-4981-b7a7-5e366761dbce","super_type":"SUPERTYPE_UNSPECIFIED","total_offer_discount":80,"discount_share":{"swiggy_discount":28,"store_discount":52,"alliance_discount":0},"discount_type":"PERCENTAGE","description":"40% off","fixed_charges":{"gp":{"id":"","final_price":0}}}] | H69: 2023-12-02 13:46:34 | I69: 2023-12-02 13:46:52 | J69: 21191609 | K69: Delivered | L69: SIKENDAR KUMAR YADAV | M69: 2675 | N69: Subway | O69: 36, 3rd Store, 7th Sector, 14th main, HSR Layout | P69: 7th Sector | Q69: Bangalore | R69: 2671 | S69: =Table2[[#This Row],[delivery_time_in_seconds]]/60 -> 44.516667 | T69: 354 | U69: 354 | V69: 354 | W69: 398 | X69: 32 | Y69: 12.9118135,77.637958 | Z69: =IF(Table2[[#This Row],[restaurant_customer_distance]]<=2,"0-2 Km",IF(Table2[[#This Row],[restaurant_customer_distance]]<=5,"2-5 Km",IF(Table2[[#This Row],[restaurant_customer_distance]]<=8,"5-8 Km","8+Km"))) -> 0-2 Km | AA69: 1.9 | AB69: UPICollect | AC69: Hsr Layout | AD69: FALSE | AE69: 0 | AF69: =EOMONTH(H69,-1)+1 -> 45261 | AG69: =IFERROR(VLOOKUP(AC69,#REF!,2,0),AC69) -> Hsr Layout | AH69: =IFERROR(TRIM(_xlfn.TEXTBEFORE(N69,"-")),N69) -> Subway | AI69: =_xlfn.TEXTBEFORE(Y69,",") -> 12.9118135 | AJ69: =_xlfn.TEXTAFTER(Y69,",") -> 77.637958
A70: 159955886050893 | B70: =_xlfn.XLOOKUP(Table2[[#This Row],[order_id]],swiggy_order_items!A70:A239,swiggy_order_items!B70:B239) -> Chicken Varattiyathu | C70: =_xlfn.XLOOKUP(Table2[[#This Row],[name of the food]],swiggy_order_items!B70:B239,swiggy_order_items!E70:E239) -> Non_Veg | D70: TRUE | E70: SWIGGYIT | F70: =IFERROR(TRUNC((_xlfn.TEXTBEFORE(_xlfn.TEXTAFTER(G70,"""total_offer_discount"":"),",")),2),"NO OFFER") -> 120 | G70: [{"id":"a17455c6-6016-48b5-95c0-933ae258bf5c","super_type":"SUPERTYPE_UNSPECIFIED","total_offer_discount":120,"discount_share":{"swiggy_discount":36,"store_discount":84,"alliance_discount":0},"discount_type":"PERCENTAGE","description":"60% off","fixed_charges":{"gp":{"id":"","final_price":0}}}] | H70: 2023-11-26 13:41:26 | I70: 2023-11-26 13:41:50 | J70: 21191609 | K70: Delivered | L70: Rajasekar Reddy | M70: 81810 | N70: Tharavadu family restaurant | O70: 1st FLOOR, NO.116/1, HOSUR MAIN ROAD, MANGAMMANAPALYA CROSS, BOMMANAHALLI , Bommenahalli , Bangalore South, Bangalore Urban, Karnataka-560068 | P70: Hosur Main Road | Q70: Bangalore | R70: 1550 | S70: =Table2[[#This Row],[delivery_time_in_seconds]]/60 -> 25.833333 | T70: 284 | U70: 284 | V70: 284 | W70: 375 | X70: 41 | Y70: 12.906146,77.629745 | Z70: =IF(Table2[[#This Row],[restaurant_customer_distance]]<=2,"0-2 Km",IF(Table2[[#This Row],[restaurant_customer_distance]]<=5,"2-5 Km",IF(Table2[[#This Row],[restaurant_customer_distance]]<=8,"5-8 Km","8+Km"))) -> 2-5 Km | AA70: 3.3 | AB70: UPICollect | AC70: Bommanahalli | AD70: FALSE | AE70: 0 | AF70: =EOMONTH(H70,-1)+1 -> 45231 | AG70: =IFERROR(VLOOKUP(AC70,#REF!,2,0),AC70) -> Bommanahalli | AH70: =IFERROR(TRIM(_xlfn.TEXTBEFORE(N70,"-")),N70) -> Tharavadu family restaurant | AI70: =_xlfn.TEXTBEFORE(Y70,",") -> 12.906146 | AJ70: =_xlfn.TEXTAFTER(Y70,",") -> 77.629745
A71: 159700431113615 | B71: =_xlfn.XLOOKUP(Table2[[#This Row],[order_id]],swiggy_order_items!A71:A240,swiggy_order_items!B71:B240) -> Peanut Butter & Snicker Thickshake | C71: =_xlfn.XLOOKUP(Table2[[#This Row],[name of the food]],swiggy_order_items!B71:B240,swiggy_order_items!E71:E240) -> Veg | D71: TRUE | E71: FLATDEAL | F71: =IFERROR(TRUNC((_xlfn.TEXTBEFORE(_xlfn.TEXTAFTER(G71,"""total_offer_discount"":"),",")),2),"NO OFFER") -> 100 | G71: [{"id":"3be8626e-f3e3-4950-bcca-639767fe94cf","super_type":"SUPERTYPE_UNSPECIFIED","total_offer_discount":100,"discount_share":{"swiggy_discount":0,"store_discount":100,"alliance_discount":0},"discount_type":"FLAT","description":"FLAT100 off","fixed_charges":{"gp":{"id":"","final_price":0}}}] | H71: 2023-11-23 14:43:51 | I71: 2023-11-23 14:44:09 | J71: 21191609 | K71: Delivered | L71: Jayadev Behera | M71: 700113 | N71: The Best Thickshakes Co | O71: 1237, Sri Sai Crystal 17th cross, 5th Main Rd, HSR Layout, Bengaluru, Karnataka 560102 | P71: 5th Main Rd | Q71: Bangalore | R71: 1673 | S71: =Table2[[#This Row],[delivery_time_in_seconds]]/60 -> 27.883333 | T71: 455 | U71: 455 | V71: 455 | W71: 530 | X71: 29 | Y71: 12.912028,77.632327 | Z71: =IF(Table2[[#This Row],[restaurant_customer_distance]]<=2,"0-2 Km",IF(Table2[[#This Row],[restaurant_customer_distance]]<=5,"2-5 Km",IF(Table2[[#This Row],[restaurant_customer_distance]]<=8,"5-8 Km","8+Km"))) -> 2-5 Km | AA71: 2.3 | AB71: UPICollect | AC71: HSR | AD71: FALSE | AE71: 0 | AF71: =EOMONTH(H71,-1)+1 -> 45231 | AG71: =IFERROR(VLOOKUP(AC71,#REF!,2,0),AC71) -> HSR | AH71: =IFERROR(TRIM(_xlfn.TEXTBEFORE(N71,"-")),N71) -> The Best Thickshakes Co | AI71: =_xlfn.TEXTBEFORE(Y71,",") -> 12.912028 | AJ71: =_xlfn.TEXTAFTER(Y71,",") -> 77.632327
A72: 159024606634682 | B72: =_xlfn.XLOOKUP(Table2[[#This Row],[order_id]],swiggy_order_items!A72:A241,swiggy_order_items!B72:B241) -> Idiyappam | C72: =_xlfn.XLOOKUP(Table2[[#This Row],[name of the food]],swiggy_order_items!B72:B241,swiggy_order_items!E72:E241) -> Veg | D72: TRUE | E72: KINGK50 | F72: =IFERROR(TRUNC((_xlfn.TEXTBEFORE(_xlfn.TEXTAFTER(G72,"""total_offer_discount"":"),",")),2),"NO OFFER") -> 50.01 | G72: [{"id":"03ca3c14-fff6-467e-ae52-d8c251b67a76","super_type":"SUPERTYPE_UNSPECIFIED","total_offer_discount":50.01,"discount_share":{"swiggy_discount":50.01,"store_discount":0,"alliance_discount":0},"discount_type":"FLAT","description":"Flat ₹200 off","fixed_charges":{"gp":{"id":"","final_price":0}},"applied_as":"SHADOW","base_offers":[{"offer_id":"92c138b0-4008-4a46-83f9-f28b6636521d","coupon_code":"WORLDCUPMANIA"}]},{"id":"92c138b0-4008-4a46-83f9-f28b6636521d","super_type":"SUPERTYPE_UNSPECIFIED","total_offer_discount":149.97,"discount_share":{"swiggy_discount":30.01,"store_discount":119.96,"alliance_discount":0},"discount_type":"FLAT","description":"FLAT150 off","fixed_charges":{"gp":{"id":"","final_price":0}}}] | H72: 2023-11-15 19:00:06 | I72: 2023-11-15 19:00:24 | J72: 21191609 | K72: Delivered | L72: MOSTAFIZAR RAHAMAN | M72: 81810 | N72: Tharavadu family restaurant | O72: 1st FLOOR, NO.116/1, HOSUR MAIN ROAD, MANGAMMANAPALYA CROSS, BOMMANAHALLI , Bommenahalli , Bangalore South, Bangalore Urban, Karnataka-560068 | P72: Hosur Main Road | Q72: Bangalore | R72: 2047 | S72: =Table2[[#This Row],[delivery_time_in_seconds]]/60 -> 34.116667 | T72: 380 | U72: 380 | V72: 380 | W72: 540 | X72: 44 | Y72: 12.906146,77.629745 | Z72: =IF(Table2[[#This Row],[restaurant_customer_distance]]<=2,"0-2 Km",IF(Table2[[#This Row],[restaurant_customer_distance]]<=5,"2-5 Km",IF(Table2[[#This Row],[restaurant_customer_distance]]<=8,"5-8 Km","8+Km"))) -> 2-5 Km | AA72: 3.3 | AB72: UPICollect | AC72: Bommanahalli | AD72: FALSE | AE72: 0 | AF72: =EOMONTH(H72,-1)+1 -> 45231 | AG72: =IFERROR(VLOOKUP(AC72,#REF!,2,0),AC72) -> Bommanahalli | AH72: =IFERROR(TRIM(_xlfn.TEXTBEFORE(N72,"-")),N72) -> Tharavadu family restaurant | AI72: =_xlfn.TEXTBEFORE(Y72,",") -> 12.906146 | AJ72: =_xlfn.TEXTAFTER(Y72,",") -> 77.629745
A73: 158421216354293 | B73: =_xlfn.XLOOKUP(Table2[[#This Row],[order_id]],swiggy_order_items!A73:A242,swiggy_order_items!B73:B242) -> Chicken Darjeeling Steam Momo | C73: =_xlfn.XLOOKUP(Table2[[#This Row],[name of the food]],swiggy_order_items!B73:B242,swiggy_order_items!E73:E242) -> Non_Veg | D73: FALSE | E73: No coupon | F73: =IFERROR(TRUNC((_xlfn.TEXTBEFORE(_xlfn.TEXTAFTER(G73,"""total_offer_discount"":"),",")),2),"NO OFFER") -> NO OFFER | G73: "total_offer_discount":NO OFFER, | H73: 2023-11-08 19:23:36 | I73: 2023-11-08 19:23:57 | J73: 21191609 | K73: Delivered | L73: Eresha | M73: 244004 | N73: Wow! Momo | O73: WOW MOMO NO1 120 14th main road 5th sector HSR layout Bangalore BTM layout BBMP south Karnataka 560102 | P73: 5th sector | Q73: Bangalore | R73: 2006 | S73: =Table2[[#This Row],[delivery_time_in_seconds]]/60 -> 33.433333 | T73: 221 | U73: 221 | V73: 221 | W73: 268 | X73: 32 | Y73: 12.9161961,77.6377847 | Z73: =IF(Table2[[#This Row],[restaurant_customer_distance]]<=2,"0-2 Km",IF(Table2[[#This Row],[restaurant_customer_distance]]<=5,"2-5 Km",IF(Table2[[#This Row],[restaurant_customer_distance]]<=8,"5-8 Km","8+Km"))) -> 2-5 Km | AA73: 2.1 | AB73: UPICollect | AC73: HSR Layout | AD73: FALSE | AE73: 0 | AF73: =EOMONTH(H73,-1)+1 -> 45231 | AG73: =IFERROR(VLOOKUP(AC73,#REF!,2,0),AC73) -> HSR Layout | AH73: =IFERROR(TRIM(_xlfn.TEXTBEFORE(N73,"-")),N73) -> Wow! Momo | AI73: =_xlfn.TEXTBEFORE(Y73,",") -> 12.9161961 | AJ73: =_xlfn.TEXTAFTER(Y73,",") -> 77.6377847
... A93: 177265186487 | B93: =_xlfn.XLOOKUP(Table2[[#This Row],[order_id]],swiggy_order_items!A93:A262,swiggy_order_items!B93:B262) -> Firecracker Wings | C93: =_xlfn.XLOOKUP(Table2[[#This Row],[name of the food]],swiggy_order_items!B93:B262,swiggy_order_items!E93:E262) -> Non_Veg | D93: TRUE | E93: PARTY | F93: =IFERROR(TRUNC((_xlfn.TEXTBEFORE(_xlfn.TEXTAFTER(G93,"""total_offer_discount"":"),",")),2),"NO OFFER") -> 197 | G93: [{"id":"1178c39c-98d9-4510-b5b7-122edfb7e4fc","super_type":"SUPERTYPE_UNSPECIFIED","total_offer_discount":197,"discount_share":{"swiggy_discount":0,"store_discount":197,"alliance_discount":0},"discount_type":"PERCENTAGE","description":"10% off","fixed_charges":{"gp":{"id":"","final_price":0}}}] | H93: 2023-09-08 21:49:47 | I93: 2023-09-08 21:50:07 | J93: 21191609 | K93: Delivered | L93: Monirul Hoque | M93: 395574 | N93: Plan B | O93: No 2324, 17th Cross Road, 1st Sector, HSR Layout, Bengaluru, Karnataka 560012 | P93: 1st Sector | Q93: Bangalore | R93: 2907 | S93: =Table2[[#This Row],[delivery_time_in_seconds]]/60 -> 48.45 | T93: 1905 | U93: 1905 | V93: 1905 | W93: 1970 | X93: 37 | Y93: 12.912120631518187,77.65069759736535 | Z93: =IF(Table2[[#This Row],[restaurant_customer_distance]]<=2,"0-2 Km",IF(Table2[[#This Row],[restaurant_customer_distance]]<=5,"2-5 Km",IF(Table2[[#This Row],[restaurant_customer_distance]]<=8,"5-8 Km","8+Km"))) -> 0-2 Km | AA93: 0.7 | AB93: UPICollect | AC93: HSR Layout | AD93: TRUE | AE93: 0 | AF93: =EOMONTH(H93,-1)+1 -> 45170 | AG93: =IFERROR(VLOOKUP(AC93,#REF!,2,0),AC93) -> HSR Layout | AH93: =IFERROR(TRIM(_xlfn.TEXTBEFORE(N93,"-")),N93) -> Plan B | AI93: =_xlfn.TEXTBEFORE(Y93,",") -> 12.912120631518187 | AJ93: =_xlfn.TEXTAFTER(Y93,",") -> 77.65069759736535
A94: 176793394432 | B94: =_xlfn.XLOOKUP(Table2[[#This Row],[order_id]],swiggy_order_items!A94:A263,swiggy_order_items!B94:B263) -> Chocolate And Love Smoothie Bowl | C94: =_xlfn.XLOOKUP(Table2[[#This Row],[name of the food]],swiggy_order_items!B94:B263,swiggy_order_items!E94:E263) -> Veg | D94: TRUE | E94: TRYNEW | F94: =IFERROR(TRUNC((_xlfn.TEXTBEFORE(_xlfn.TEXTAFTER(G94,"""total_offer_discount"":"),",")),2),"NO OFFER") -> 39.8 | G94: [{"id":"6ca97531-301c-4632-a58f-646d0afd9e01","super_type":"SUPERTYPE_UNSPECIFIED","total_offer_discount":39.8,"discount_share":{"swiggy_discount":0,"store_discount":39.8,"alliance_discount":0},"discount_type":"PERCENTAGE","description":"10% off","fixed_charges":{"gp":{"id":"","final_price":0}}}] | H94: 2023-09-03 10:46:35 | I94: =Table2[[#This Row],[order_time]] -> 2023-09-03 10:46:35 | J94: 21191609 | K94: Delivered | L94: Priyabrata Jena | M94: 298606 | N94: Drunken Monkey | O94: No.634 ground floor,5th cross,15th main ,4th block,kormangala (near chinmaya vidyalaya school),bangalore 560034 | P94: 4th Block | Q94: Bangalore | R94: 1712 | S94: =Table2[[#This Row],[delivery_time_in_seconds]]/60 -> 28.533333 | T94: 399 | U94: 399 | V94: 399 | W94: 398 | X94: 44 | Y94: 12.934488559072948,77.62886978481599 | Z94: =IF(Table2[[#This Row],[restaurant_customer_distance]]<=2,"0-2 Km",IF(Table2[[#This Row],[restaurant_customer_distance]]<=5,"2-5 Km",IF(Table2[[#This Row],[restaurant_customer_distance]]<=8,"5-8 Km","8+Km"))) -> 2-5 Km | AA94: 4.4 | AB94: UPIIntent | AC94: Koramangala | AD94: FALSE | AE94: 0 | AF94: =EOMONTH(H94,-1)+1 -> 45170 | AG94: =IFERROR(VLOOKUP(AC94,#REF!,2,0),AC94) -> Koramangala | AH94: =IFERROR(TRIM(_xlfn.TEXTBEFORE(N94,"-")),N94) -> Drunken Monkey | AI94: =_xlfn.TEXTBEFORE(Y94,",") -> 12.934488559072948 | AJ94: =_xlfn.TEXTAFTER(Y94,",") -> 77.62886978481599
A95: 176745115332 | B95: =_xlfn.XLOOKUP(Table2[[#This Row],[order_id]],swiggy_order_items!A95:A264,swiggy_order_items!B95:B264) -> Veg. Ramyun | C95: =_xlfn.XLOOKUP(Table2[[#This Row],[name of the food]],swiggy_order_items!B95:B264,swiggy_order_items!E95:E264) -> Veg | D95: TRUE | E95: TRYNEW | F95: =IFERROR(TRUNC((_xlfn.TEXTBEFORE(_xlfn.TEXTAFTER(G95,"""total_offer_discount"":"),",")),2),"NO OFFER") -> 100 | G95: [{"id":"f80596b9-9db2-47d0-98be-dbdde4df4855","super_type":"SUPERTYPE_UNSPECIFIED","total_offer_discount":100,"discount_share":{"swiggy_discount":0,"store_discount":100,"alliance_discount":0},"discount_type":"PERCENTAGE","description":"50% off","fixed_charges":{"gp":{"id":"","final_price":0}}}] | H95: 2023-09-02 21:21:56 | I95: =Table2[[#This Row],[order_time]] -> 2023-09-02 21:21:56 | J95: 21191609 | K95: Delivered | L95: Manoj Kumar H M | M95: 254655 | N95: Daily Sushi | O95: No.1212, SBM Fortune, 4th Floor, 22nd Cross Road, 14th Main Rd, 3rd Sector, HSR Layout, Bengaluru, Karnataka 560102, India | P95: 3rd Sector | Q95: Bangalore | R95: 2738 | S95: =Table2[[#This Row],[delivery_time_in_seconds]]/60 -> 45.633333 | T95: 359 | U95: 359 | V95: 359 | W95: 400 | X95: 36 | Y95: 12.909368,77.638656 | Z95: =IF(Table2[[#This Row],[restaurant_customer_distance]]<=2,"0-2 Km",IF(Table2[[#This Row],[restaurant_customer_distance]]<=5,"2-5 Km",IF(Table2[[#This Row],[restaurant_customer_distance]]<=8,"5-8 Km","8+Km"))) -> 2-5 Km | AA95: 2.1 | AB95: UPIIntent | AC95: HSR Layout | AD95: FALSE | AE95: 0 | AF95: =EOMONTH(H95,-1)+1 -> 45170 | AG95: =IFERROR(VLOOKUP(AC95,#REF!,2,0),AC95) -> HSR Layout | AH95: =IFERROR(TRIM(_xlfn.TEXTBEFORE(N95,"-")),N95) -> Daily Sushi | AI95: =_xlfn.TEXTBEFORE(Y95,",") -> 12.909368 | AJ95: =_xlfn.TEXTAFTER(Y95,",") -> 77.638656
A96: 176716772573 | B96: =_xlfn.XLOOKUP(Table2[[#This Row],[order_id]],swiggy_order_items!A96:A265,swiggy_order_items!B96:B265) -> Trapper Creek | C96: =_xlfn.XLOOKUP(Table2[[#This Row],[name of the food]],swiggy_order_items!B96:B265,swiggy_order_items!E96:E265) -> Non_Veg | D96: TRUE | E96: WEEKENDS | F96: =IFERROR(TRUNC((_xlfn.TEXTBEFORE(_xlfn.TEXTAFTER(G96,"""total_offer_discount"":"),",")),2),"NO OFFER") -> 125 | G96: [{"id":"e7ca910b-b1f7-4fca-81aa-29bb167a90b0","super_type":"SUPERTYPE_UNSPECIFIED","total_offer_discount":125,"discount_share":{"swiggy_discount":50,"store_discount":75,"alliance_discount":0},"discount_type":"FLAT","description":"Flat ₹125 off","fixed_charges":{"gp":{"id":"","final_price":0}}}] | H96: 2023-09-02 13:29:33 | I96: =Table2[[#This Row],[order_time]] -> 2023-09-02 13:29:33 | J96: 21191609 | K96: Delivered | L96: Raghunatha | M96: 341895 | N96: Burger Seigneur | O96: NO.35, 80FEET ROAD, HAL 3RD STAGE, BANGALORE B.B.M.P East Karnataka 560075 | P96: Indiranagar | Q96: Bangalore | R96: 2483 | S96: =Table2[[#This Row],[delivery_time_in_seconds]]/60 -> 41.383333 | T96: 356 | U96: 356 | V96: 356 | W96: 460 | X96: 34 | Y96: 12.97107,77.647521 | Z96: =IF(Table2[[#This Row],[restaurant_customer_distance]]<=2,"0-2 Km",IF(Table2[[#This Row],[restaurant_customer_distance]]<=5,"2-5 Km",IF(Table2[[#This Row],[restaurant_customer_distance]]<=8,"5-8 Km","8+Km"))) -> 0-2 Km | AA96: 1.5 | AB96: UPIIntent | AC96: Indiranagar | AD96: TRUE | AE96: 0 | AF96: =EOMONTH(H96,-1)+1 -> 45170 | AG96: =IFERROR(VLOOKUP(AC96,#REF!,2,0),AC96) -> Indiranagar | AH96: =IFERROR(TRIM(_xlfn.TEXTBEFORE(N96,"-")),N96) -> Burger Seigneur | AI96: =_xlfn.TEXTBEFORE(Y96,",") -> 12.97107 | AJ96: =_xlfn.TEXTAFTER(Y96,",") -> 77.647521
A97: 176451044220 | B97: =_xlfn.XLOOKUP(Table2[[#This Row],[order_id]],swiggy_order_items!A97:A266,swiggy_order_items!B97:B266) -> Spaghetti Carbonara Chicken | C97: =_xlfn.XLOOKUP(Table2[[#This Row],[name of the food]],swiggy_order_items!B97:B266,swiggy_order_items!E97:E266) -> Non_Veg | D97: FALSE | E97: No coupon | F97: =IFERROR(TRUNC((_xlfn.TEXTBEFORE(_xlfn.TEXTAFTER(G97,"""total_offer_discount"":"),",")),2),"NO OFFER") -> NO OFFER | G97: "total_offer_discount":NO OFFER, | H97: 2023-08-30 11:40:45 | I97: =Table2[[#This Row],[order_time]] -> 2023-08-30 11:40:45 | J97: 21191609 | K97: Delivered | L97: Kumar R | M97: 47603 | N97: Truffles | O97: BUNDL TECHNOLOGIES PVT LTD, 1ST FLOOR, SITE NO.164, KHATA NO.684, PID NO: 658/668/684/1/164/1, BELLANDURVILLAGE, VARTHUR HOBLI, BANGALORE EAST TALUK 560103 | P97: Green Glen Layout | Q97: Bangalore | R97: 1839 | S97: =Table2[[#This Row],[delivery_time_in_seconds]]/60 -> 30.65 | T97: 301 | U97: 301 | V97: 301 | W97: 261.90997 | X97: 39 | Y97: 12.927332,77.669014 | Z97: =IF(Table2[[#This Row],[restaurant_customer_distance]]<=2,"0-2 Km",IF(Table2[[#This Row],[restaurant_customer_distance]]<=5,"2-5 Km",IF(Table2[[#This Row],[restaurant_customer_distance]]<=8,"5-8 Km","8+Km"))) -> 2-5 Km | AA97: 4.9 | AB97: UPIIntent | AC97: Bellandur | AD97: FALSE | AE97: 0 | AF97: =EOMONTH(H97,-1)+1 -> 45139 | AG97: =IFERROR(VLOOKUP(AC97,#REF!,2,0),AC97) -> Bellandur | AH97: =IFERROR(TRIM(_xlfn.TEXTBEFORE(N97,"-")),N97) -> Truffles | AI97: =_xlfn.TEXTBEFORE(Y97,",") -> 12.927332 | AJ97: =_xlfn.TEXTAFTER(Y97,",") -> 77.669014
A98: 176221057630 | B98: =_xlfn.XLOOKUP(Table2[[#This Row],[order_id]],swiggy_order_items!A98:A267,swiggy_order_items!B98:B267) -> Istah's Chicken Shawarma in Rumali | C98: =_xlfn.XLOOKUP(Table2[[#This Row],[name of the food]],swiggy_order_items!B98:B267,swiggy_order_items!E98:E267) -> Non_Veg | D98: FALSE | E98: No coupon | F98: =IFERROR(TRUNC((_xlfn.TEXTBEFORE(_xlfn.TEXTAFTER(G98,"""total_offer_discount"":"),",")),2),"NO OFFER") -> NO OFFER | G98: "total_offer_discount":NO OFFER, | H98: 2023-08-27 19:47:38 | I98: =Table2[[#This Row],[order_time]] -> 2023-08-27 19:47:38 | J98: 21191609 | K98: Delivered | L98: Paresh Kumar Mohanty | M98: 498292 | N98: Istah - The Mediterranean Way | O98: 88/1, Ward No, 66, Swiggy Koramangala Super Hub building, Sarjapur Road, Jakkasandra Village, Bangalore 560034 | P98: 1st Block | Q98: Bangalore | R98: 2187 | S98: =Table2[[#This Row],[delivery_time_in_seconds]]/60 -> 36.45 | T98: 164 | U98: 164 | V98: 164 | W98: 199 | X98: 41 | Y98: 12.925114189248388,77.6370633020997 | Z98: =IF(Table2[[#This Row],[restaurant_customer_distance]]<=2,"0-2 Km",IF(Table2[[#This Row],[restaurant_customer_distance]]<=5,"2-5 Km",IF(Table2[[#This Row],[restaurant_customer_distance]]<=8,"5-8 Km","8+Km"))) -> 2-5 Km | AA98: 3.1 | AB98: UPIIntent | AC98: Koramangala | AD98: FALSE | AE98: 0 | AF98: =EOMONTH(H98,-1)+1 -> 45139 | AG98: =IFERROR(VLOOKUP(AC98,#REF!,2,0),AC98) -> Koramangala | AH98: =IFERROR(TRIM(_xlfn.TEXTBEFORE(N98,"-")),N98) -> Istah | AI98: =_xlfn.TEXTBEFORE(Y98,",") -> 12.925114189248388 | AJ98: =_xlfn.TEXTAFTER(Y98,",") -> 77.6370633020997
A99: 175968970700 | B99: =_xlfn.XLOOKUP(Table2[[#This Row],[order_id]],swiggy_order_items!A99:A268,swiggy_order_items!B99:B268) -> Belgian Chocolate Milk Shake | C99: =_xlfn.XLOOKUP(Table2[[#This Row],[name of the food]],swiggy_order_items!B99:B268,swiggy_order_items!E99:E268) -> Veg | D99: TRUE | E99: JUMBO | F99: =IFERROR(TRUNC((_xlfn.TEXTBEFORE(_xlfn.TEXTAFTER(G99,"""total_offer_discount"":"),",")),2),"NO OFFER") -> 109.5 | G99: [{"id":"299a513a-6f7c-458c-86bb-38f205d6dbd9","super_type":"SUPERTYPE_UNSPECIFIED","total_offer_discount":109.5,"discount_share":{"swiggy_discount":21.9,"store_discount":87.6,"alliance_discount":0},"discount_type":"PERCENTAGE","description":"25% off","fixed_charges":{"gp":{"id":"","final_price":0}}}] | H99: 2023-08-24 21:46:11 | I99: =Table2[[#This Row],[order_time]] -> 2023-08-24 21:46:11 | J99: 21191609 | K99: cancelled | M99: 405903 | N99: The Thick Shake Factory | O99: #NO.104, SHIVALAYA, 17TH C MAIN ROAD, 5TH CROSS, KORAMANGALA, 5 TH BLOCK, BANGALORE,560095,Next to Acura Speciality Hospital,pivotal 4th floor. Karnataka - 560095 | P99: 5th Block | Q99: Bangalore | R99: 0 | S99: =Table2[[#This Row],[delivery_time_in_seconds]]/60 -> 0 | T99: 369 | U99: 369 | V99: 369 | W99: 438 | X99: 55 | Y99: 12.935401,77.620598 | Z99: =IF(Table2[[#This Row],[restaurant_customer_distance]]<=2,"0-2 Km",IF(Table2[[#This Row],[restaurant_customer_distance]]<=5,"2-5 Km",IF(Table2[[#This Row],[restaurant_customer_distance]]<=8,"5-8 Km","8+Km"))) -> 5-8 Km | AA99: 5.4 | AB99: UPIIntent | AC99: Koramangala | AD99: FALSE | AE99: 0 | AF99: =EOMONTH(H99,-1)+1 -> 45139 | AG99: =IFERROR(VLOOKUP(AC99,#REF!,2,0),AC99) -> Koramangala | AH99: =IFERROR(TRIM(_xlfn.TEXTBEFORE(N99,"-")),N99) -> The Thick Shake Factory | AI99: =_xlfn.TEXTBEFORE(Y99,",") -> 12.935401 | AJ99: =_xlfn.TEXTAFTER(Y99,",") -> 77.620598
A100: 175192473312 | B100: =_xlfn.XLOOKUP(Table2[[#This Row],[order_id]],swiggy_order_items!A100:A269,swiggy_order_items!B100:B269) -> Panoor Special Chicken Leg Fry | C100: =_xlfn.XLOOKUP(Table2[[#This Row],[name of the food]],swiggy_order_items!B100:B269,swiggy_order_items!E100:E269) -> Non_Veg | D100: FALSE | E100: No coupon | F100: =IFERROR(TRUNC((_xlfn.TEXTBEFORE(_xlfn.TEXTAFTER(G100,"""total_offer_discount"":"),",")),2),"NO OFFER") -> NO OFFER | G100: "total_offer_discount":NO OFFER, | H100: 2023-08-15 22:04:33 | I100: =Table2[[#This Row],[order_time]] -> 2023-08-15 22:04:33 | J100: 21191609 | K100: Delivered | L100: Asif Alli | M100: 64914 | N100: Kerala Panoor Restaurant | O100: Devarabeesanahalli Flyover, Devarabisanahalli, Bellandur, Bengaluru, Karnataka 560103 | P100: Devarabisanahalli | Q100: Bangalore | R100: 1654 | S100: =Table2[[#This Row],[delivery_time_in_seconds]]/60 -> 27.566667 | T100: 504 | U100: 504 | V100: 504 | W100: 465 | X100: 54 | Y100: 12.930556,77.68499199999997 | Z100: =IF(Table2[[#This Row],[restaurant_customer_distance]]<=2,"0-2 Km",IF(Table2[[#This Row],[restaurant_customer_distance]]<=5,"2-5 Km",IF(Table2[[#This Row],[restaurant_customer_distance]]<=8,"5-8 Km","8+Km"))) -> 2-5 Km | AA100: 5 | AB100: UPIIntent | AC100: Bellandur | AD100: FALSE | AE100: 0 | AF100: =EOMONTH(H100,-1)+1 -> 45139 | AG100: =IFERROR(VLOOKUP(AC100,#REF!,2,0),AC100) -> Bellandur | AH100: =IFERROR(TRIM(_xlfn.TEXTBEFORE(N100,"-")),N100) -> Kerala Panoor Restaurant | AI100: =_xlfn.TEXTBEFORE(Y100,",") -> 12.930556 | AJ100: =_xlfn.TEXTAFTER(Y100,",") -> 77.68499199999997
A101: 174983850554 | B101: =_xlfn.XLOOKUP(Table2[[#This Row],[order_id]],swiggy_order_items!A101:A270,swiggy_order_items!B101:B270) -> Roasted Garlic Chicken Soup | C101: =_xlfn.XLOOKUP(Table2[[#This Row],[name of the food]],swiggy_order_items!B101:B270,swiggy_order_items!E101:E270) -> Non_Veg | D101: FALSE | E101: No coupon | F101: =IFERROR(TRUNC((_xlfn.TEXTBEFORE(_xlfn.TEXTAFTER(G101,"""total_offer_discount"":"),",")),2),"NO OFFER") -> NO OFFER | G101: "total_offer_discount":NO OFFER, | H101: 2023-08-13 12:07:31 | I101: =Table2[[#This Row],[order_time]] -> 2023-08-13 12:07:31 | J101: 21191609 | K101: Delivered | L101: Govind Shrma | M101: 6907 | N101: FreshMenu | O101: No 526/A,Ganesh Complex,Ground floor,18th Main Road,HSR 3rd sector,Bangalore:560102 | P101: 3rd Sector | Q101: Bangalore | R101: 1728 | S101: =Table2[[#This Row],[delivery_time_in_seconds]]/60 -> 28.8 | T101: 477 | U101: 477 | V101: 477 | W101: 763 | X101: 25 | Y101: 12.9054065,77.64410799999996 | Z101: =IF(Table2[[#This Row],[restaurant_customer_distance]]<=2,"0-2 Km",IF(Table2[[#This Row],[restaurant_customer_distance]]<=5,"2-5 Km",IF(Table2[[#This Row],[restaurant_customer_distance]]<=8,"5-8 Km","8+Km"))) -> 0-2 Km | AA101: 1.8 | AB101: UPIIntent | AC101: HSR Layout | AD101: FALSE | AE101: 0 | AF101: =EOMONTH(H101,-1)+1 -> 45139 | AG101: =IFERROR(VLOOKUP(AC101,#REF!,2,0),AC101) -> HSR Layout | AH101: =IFERROR(TRIM(_xlfn.TEXTBEFORE(N101,"-")),N101) -> FreshMenu | AI101: =_xlfn.TEXTBEFORE(Y101,",") -> 12.9054065 | AJ101: =_xlfn.TEXTAFTER(Y101,",") -> 77.64410799999996
A102: 174647551706 | B102: =_xlfn.XLOOKUP(Table2[[#This Row],[order_id]],swiggy_order_items!A102:A271,swiggy_order_items!B102:B271) -> Belgian Chocolate Thick Shake | C102: =_xlfn.XLOOKUP(Table2[[#This Row],[name of the food]],swiggy_order_items!B102:B271,swiggy_order_items!E102:E271) -> Veg | D102: TRUE | E102: JUMBO | F102: =IFERROR(TRUNC((_xlfn.TEXTBEFORE(_xlfn.TEXTAFTER(G102,"""total_offer_discount"":"),",")),2),"NO OFFER") -> 119.49 | G102: [{"id":"6706ebc3-55e8-475e-aba5-bc6ec3ab1f6b","super_type":"SUPERTYPE_UNSPECIFIED","total_offer_discount":119.49000000000001,"discount_share":{"swiggy_discount":23.9,"store_discount":95.59,"alliance_discount":0},"discount_type":"PERCENTAGE","description":"25% off","fixed_charges":{"gp":{"id":"","final_price":0}}}] | H102: 2023-08-09 14:42:32 | I102: =Table2[[#This Row],[order_time]] -> 2023-08-09 14:42:32 | J102: 21191609 | K102: Delivered | L102: Suresh Mahal | M102: 405912 | N102: The Thick Shake Factory | O102: #87, 14TH MAIN ROAD, 4TH SECTOR, OPP: BDA COMPLEX, HSR LAYOUT BANGALORE-560102, Sangeetha mobile showroom Besment | P102: 4th sector | Q102: Bangalore | R102: 1269 | S102: =Table2[[#This Row],[delivery_time_in_seconds]]/60 -> 21.15 | T102: 401 | U102: 401 | V102: 401 | W102: 478 | X102: 25 | Y102: 12.9125116379822,77.63817068570162 | Z102: =IF(Table2[[#This Row],[restaurant_customer_distance]]<=2,"0-2 Km",IF(Table2[[#This Row],[restaurant_customer_distance]]<=5,"2-5 Km",IF(Table2[[#This Row],[restaurant_customer_distance]]<=8,"5-8 Km","8+Km"))) -> 0-2 Km | AA102: 1.7 | AB102: UPIIntent | AC102: HSR Layout | AD102: FALSE | AE102: 0 | AF102: =EOMONTH(H102,-1)+1 -> 45139 | AG102: =IFERROR(VLOOKUP(AC102,#REF!,2,0),AC102) -> HSR Layout | AH102: =IFERROR(TRIM(_xlfn.TEXTBEFORE(N102,"-")),N102) -> The Thick Shake Factory | AI102: =_xlfn.TEXTBEFORE(Y102,",") -> 12.9125116379822 | AJ102: =_xlfn.TEXTAFTER(Y102,",") -> 77.63817068570162
A103: 174644435956 | B103: =_xlfn.XLOOKUP(Table2[[#This Row],[order_id]],swiggy_order_items!A103:A272,swiggy_order_items!B103:B272) -> Trapper Creek | C103: =_xlfn.XLOOKUP(Table2[[#This Row],[name of the food]],swiggy_order_items!B103:B272,swiggy_order_items!E103:E272) -> Non_Veg | D103: FALSE | E103: No coupon | F103: =IFERROR(TRUNC((_xlfn.TEXTBEFORE(_xlfn.TEXTAFTER(G103,"""total_offer_discount"":"),",")),2),"NO OFFER") -> NO OFFER | G103: "total_offer_discount":NO OFFER, | H103: 2023-08-09 13:50:36 | I103: =Table2[[#This Row],[order_time]] -> 2023-08-09 13:50:36 | J103: 21191609 | K103: Delivered | L103: Prakash Dalabehera | M103: 398360 | N103: Burger Seigneur | O103: #717, 10th main road 2nd cross Hosapalya Opposite of Subodhini English high school ITI layout sector 7. | P103: MANGAMMANAPALYA | Q103: Bangalore | R103: 3238 | S103: =Table2[[#This Row],[delivery_time_in_seconds]]/60 -> 53.966667 | T103: 516 | U103: 516 | V103: 516 | W103: 490 | X103: 25 | Y103: 12.9000771,77.640061 | Z103: =IF(Table2[[#This Row],[restaurant_customer_distance]]<=2,"0-2 Km",IF(Table2[[#This Row],[restaurant_customer_distance]]<=5,"2-5 Km",IF(Table2[[#This Row],[restaurant_customer_distance]]<=8,"5-8 Km","8+Km"))) -> 2-5 Km | AA103: 2.8 | AB103: UPIIntent | AC103: ITI layout, Hosapalya | AD103: FALSE | AE103: 0 | AF103: =EOMONTH(H103,-1)+1 -> 45139 | AG103: =IFERROR(VLOOKUP(AC103,#REF!,2,0),AC103) -> ITI layout, Hosapalya | AH103: =IFERROR(TRIM(_xlfn.TEXTBEFORE(N103,"-")),N103) -> Burger Seigneur | AI103: =_xlfn.TEXTBEFORE(Y103,",") -> 12.9000771 | AJ103: =_xlfn.TEXTAFTER(Y103,",") -> 77.640061
A104: 174559415025 | B104: =_xlfn.XLOOKUP(Table2[[#This Row],[order_id]],swiggy_order_items!A104:A273,swiggy_order_items!B104:B273) -> Americano Pasta Non-veg | C104: =_xlfn.XLOOKUP(Table2[[#This Row],[name of the food]],swiggy_order_items!B104:B273,swiggy_order_items!E104:E273) -> Non_Veg | D104: TRUE | E104: TRYNEW | F104: =IFERROR(TRUNC((_xlfn.TEXTBEFORE(_xlfn.TEXTAFTER(G104,"""total_offer_discount"":"),",")),2),"NO OFFER") -> 100 | G104: [{"id":"0fefcb58-9f41-444e-9e59-52c620b546b5","super_type":"SUPERTYPE_UNSPECIFIED","total_offer_discount":100,"discount_share":{"swiggy_discount":25,"store_discount":75,"alliance_discount":0},"discount_type":"PERCENTAGE","description":"50% off","fixed_charges":{"gp":{"id":"","final_price":0}}}] | H104: 2023-08-08 14:13:36 | I104: =Table2[[#This Row],[order_time]] -> 2023-08-08 14:13:36 | J104: 21191609 | K104: Delivered | L104: Bimbadhar Sahoo | M104: 394626 | N104: La Pino'z Pizza | O104: La Pino'z Pizza, #11/50/3, Ambalipura, Village, Sarjapur - Marathahalli Rd, Bengaluru, Karnataka 560103 | P104: Sarjapur - Marathahalli Rd | Q104: Bangalore | R104: 1585 | S104: =Table2[[#This Row],[delivery_time_in_seconds]]/60 -> 26.416667 | T104: 171 | U104: 171 | V104: 171 | W104: 225 | X104: 25 | Y104: 12.919644,77.667114 | Z104: =IF(Table2[[#This Row],[restaurant_customer_distance]]<=2,"0-2 Km",IF(Table2[[#This Row],[restaurant_customer_distance]]<=5,"2-5 Km",IF(Table2[[#This Row],[restaurant_customer_distance]]<=8,"5-8 Km","8+Km"))) -> 2-5 Km | AA104: 2.8 | AB104: UPIIntent | AC104: Bellandur | AD104: FALSE | AE104: 0 | AF104: =EOMONTH(H104,-1)+1 -> 45139 | AG104: =IFERROR(VLOOKUP(AC104,#REF!,2,0),AC104) -> Bellandur | AH104: =IFERROR(TRIM(_xlfn.TEXTBEFORE(N104,"-")),N104) -> La Pino'z Pizza | AI104: =_xlfn.TEXTBEFORE(Y104,",") -> 12.919644 | AJ104: =_xlfn.TEXTAFTER(Y104,",") -> 77.667114
A105: 174376605060 | B105: =_xlfn.XLOOKUP(Table2[[#This Row],[order_id]],swiggy_order_items!A105:A274,swiggy_order_items!B105:B274) -> Non Veg Club S/w | C105: =_xlfn.XLOOKUP(Table2[[#This Row],[name of the food]],swiggy_order_items!B105:B274,swiggy_order_items!E105:E274) -> Non_Veg | D105: FALSE | E105: No coupon | F105: =IFERROR(TRUNC((_xlfn.TEXTBEFORE(_xlfn.TEXTAFTER(G105,"""total_offer_discount"":"),",")),2),"NO OFFER") -> NO OFFER | G105: "total_offer_discount":NO OFFER, | H105: 2023-08-06 11:26:46 | I105: =Table2[[#This Row],[order_time]] -> 2023-08-06 11:26:46 | J105: 21191609 | K105: Delivered | L105: MUKESH SINGH | M105: 47603 | N105: Truffles | O105: BUNDL TECHNOLOGIES PVT LTD, 1ST FLOOR, SITE NO.164, KHATA NO.684, PID NO: 658/668/684/1/164/1, BELLANDURVILLAGE, VARTHUR HOBLI, BANGALORE EAST TALUK 560103 | P105: Green Glen Layout | Q105: Bangalore | R105: 1720 | S105: =Table2[[#This Row],[delivery_time_in_seconds]]/60 -> 28.666667 | T105: 645 | U105: 645 | V105: 645 | W105: 523.83997 | X105: 35 | Y105: 12.927332,77.66901400000006 | Z105: =IF(Table2[[#This Row],[restaurant_customer_distance]]<=2,"0-2 Km",IF(Table2[[#This Row],[restaurant_customer_distance]]<=5,"2-5 Km",IF(Table2[[#This Row],[restaurant_customer_distance]]<=8,"5-8 Km","8+Km"))) -> 2-5 Km | AA105: 4.1 | AB105: UPIIntent | AC105: Bellandur | AD105: TRUE | AE105: 0 | AF105: =EOMONTH(H105,-1)+1 -> 45139 | AG105: =IFERROR(VLOOKUP(AC105,#REF!,2,0),AC105) -> Bellandur | AH105: =IFERROR(TRIM(_xlfn.TEXTBEFORE(N105,"-")),N105) -> Truffles | AI105: =_xlfn.TEXTBEFORE(Y105,",") -> 12.927332 | AJ105: =_xlfn.TEXTAFTER(Y105,",") -> 77.66901400000006
A106: 172557699296 | B106: =_xlfn.XLOOKUP(Table2[[#This Row],[order_id]],swiggy_order_items!A106:A275,swiggy_order_items!B106:B275) -> Open Butter Masala Dosa | C106: =_xlfn.XLOOKUP(Table2[[#This Row],[name of the food]],swiggy_order_items!B106:B275,swiggy_order_items!E106:E275) -> Veg | D106: FALSE | E106: No coupon | F106: =IFERROR(TRUNC((_xlfn.TEXTBEFORE(_xlfn.TEXTAFTER(G106,"""total_offer_discount"":"),",")),2),"NO OFFER") -> NO OFFER | G106: "total_offer_discount":NO OFFER, | H106: 2023-07-16 10:11:39 | I106: =Table2[[#This Row],[order_time]] -> 2023-07-16 10:11:39 | J106: 21191609 | K106: Delivered | L106: Santosh Behera | M106: 660675 | N106: Cafe Amudham | O106: No. 146, 5th Block, Koramangala, Bangalore, BTM Layout , B.B.M.P South, Karnataka-560095 | P106: 5th Block Kormangala | Q106: Bangalore | R106: 2004 | S106: =Table2[[#This Row],[delivery_time_in_seconds]]/60 -> 33.4 | T106: 186 | U106: 186 | V106: 186 | W106: 159 | X106: 45 | Y106: 12.933842204939534,77.61976898008312 | Z106: =IF(Table2[[#This Row],[restaurant_customer_distance]]<=2,"0-2 Km",IF(Table2[[#This Row],[restaurant_customer_distance]]<=5,"2-5 Km",IF(Table2[[#This Row],[restaurant_customer_distance]]<=8,"5-8 Km","8+Km"))) -> 5-8 Km | AA106: 5.8 | AB106: UPIIntent | AC106: Koramangala | AD106: FALSE | AE106: 0 | AF106: =EOMONTH(H106,-1)+1 -> 45108 | AG106: =IFERROR(VLOOKUP(AC106,#REF!,2,0),AC106) -> Koramangala | AH106: =IFERROR(TRIM(_xlfn.TEXTBEFORE(N106,"-")),N106) -> Cafe Amudham | AI106: =_xlfn.TEXTBEFORE(Y106,",") -> 12.933842204939534 | AJ106: =_xlfn.TEXTAFTER(Y106,",") -> 77.61976898008312
A107: 171953923401 | B107: =_xlfn.XLOOKUP(Table2[[#This Row],[order_id]],swiggy_order_items!A107:A276,swiggy_order_items!B107:B276) -> Dark Chocolate Cake [350 Grams, Serves 3] | C107: =_xlfn.XLOOKUP(Table2[[#This Row],[name of the food]],swiggy_order_items!B107:B276,swiggy_order_items!E107:E276) -> Non_Veg | D107: FALSE | E107: No coupon | F107: =IFERROR(TRUNC((_xlfn.TEXTBEFORE(_xlfn.TEXTAFTER(G107,"""total_offer_discount"":"),",")),2),"NO OFFER") -> NO OFFER | G107: "total_offer_discount":NO OFFER, | H107: 2023-07-09 10:28:44 | I107: =Table2[[#This Row],[order_time]] -> 2023-07-09 10:28:44 | J107: 21191609 | K107: Delivered | L107: Vivek Kumar | M107: 416272 | N107: Table for Tous | O107: 146, 2nd Floor, HSR Layout, Sector 5, Ring Road, Bangalore, BTM Layout , B.B.M.P South, Karnataka - 560102 | P107: 4th Sector | Q107: Bangalore | R107: 2648 | S107: =Table2[[#This Row],[delivery_time_in_seconds]]/60 -> 44.133333 | T107: 1136 | U107: 1136 | V107: 1136 | W107: 1050 | X107: 29 | Y107: 12.916462690900852,77.63573539639873 | Z107: =IF(Table2[[#This Row],[restaurant_customer_distance]]<=2,"0-2 Km",IF(Table2[[#This Row],[restaurant_customer_distance]]<=5,"2-5 Km",IF(Table2[[#This Row],[restaurant_customer_distance]]<=8,"5-8 Km","8+Km"))) -> 0-2 Km | AA107: 1.7 | AB107: UPIIntent | AC107: HSR Layout | AD107: FALSE | AE107: 0 | AF107: =EOMONTH(H107,-1)+1 -> 45108 | AG107: =IFERROR(VLOOKUP(AC107,#REF!,2,0),AC107) -> HSR Layout | AH107: =IFERROR(TRIM(_xlfn.TEXTBEFORE(N107,"-")),N107) -> Table for Tous | AI107: =_xlfn.TEXTBEFORE(Y107,",") -> 12.916462690900852 | AJ107: =_xlfn.TEXTAFTER(Y107,",") -> 77.63573539639873
A108: 171863054117 | B108: =_xlfn.XLOOKUP(Table2[[#This Row],[order_id]],swiggy_order_items!A108:A277,swiggy_order_items!B108:B277) -> Open Butter Masala Dosa | C108: =_xlfn.XLOOKUP(Table2[[#This Row],[name of the food]],swiggy_order_items!B108:B277,swiggy_order_items!E108:E277) -> Veg | D108: TRUE | E108: TRYNEW | F108: =IFERROR(TRUNC((_xlfn.TEXTBEFORE(_xlfn.TEXTAFTER(G108,"""total_offer_discount"":"),",")),2),"NO OFFER") -> 35.8 | G108: [{"id":"981538f4-8587-489a-8b69-63a10fd9983e","super_type":"SUPERTYPE_UNSPECIFIED","total_offer_discount":35.8,"discount_share":{"swiggy_discount":7.16,"store_discount":28.64,"alliance_discount":0},"discount_type":"PERCENTAGE","description":"20% off","fixed_charges":{"gp":{"id":"","final_price":0}}}] | H108: 2023-07-08 09:14:15 | I108: =Table2[[#This Row],[order_time]] -> 2023-07-08 09:14:15 | J108: 21191609 | K108: Delivered | L108: Gnanam | M108: 660675 | N108: Cafe Amudham | O108: No. 146, 5th Block, Koramangala, Bangalore, BTM Layout , B.B.M.P South, Karnataka-560095 | P108: 5th Block Kormangala | Q108: Bangalore | R108: 1734 | S108: =Table2[[#This Row],[delivery_time_in_seconds]]/60 -> 28.9 | T108: 170 | U108: 170 | V108: 170 | W108: 179 | X108: 47 | Y108: 12.933842204939534,77.61976898008312 | Z108: =IF(Table2[[#This Row],[restaurant_customer_distance]]<=2,"0-2 Km",IF(Table2[[#This Row],[restaurant_customer_distance]]<=5,"2-5 Km",IF(Table2[[#This Row],[restaurant_customer_distance]]<=8,"5-8 Km","8+Km"))) -> 5-8 Km | AA108: 6 | AB108: UPIIntent | AC108: Koramangala | AD108: TRUE | AE108: 0 | AF108: =EOMONTH(H108,-1)+1 -> 45108 | AG108: =IFERROR(VLOOKUP(AC108,#REF!,2,0),AC108) -> Koramangala | AH108: =IFERROR(TRIM(_xlfn.TEXTBEFORE(N108,"-")),N108) -> Cafe Amudham | AI108: =_xlfn.TEXTBEFORE(Y108,",") -> 12.933842204939534 | AJ108: =_xlfn.TEXTAFTER(Y108,",") -> 77.61976898008312

Sheet pivot_table
D1: Monthly wise revenue distribution
D3: Row Labels | E3: Sum of net_total
A4: What proportion of total orders utilized a coupon ? | D4: 45108 | E4: 1492 | G4: Area wise Revenue
D5: Non_Veg | E5: 1136
A6: Row Labels | B6: Count of order_id | D6: Veg | E6: 356 | G6: Row Labels | H6: Sum of net_total
A7: FALSE | B7: 17 | D7: 45139 | E7: 3548 | G7: 1st Block | H7: 164
A8: TRUE | B8: 28 | D8: Non_Veg | E8: 2778 | G8: 1st Sector | H8: 3722
D9: Veg | E9: 770 | G9: 3rd Sector | H9: 1636
D10: 45170 | E10: 6319 | G10: 4th Block | H10: 399
D11: Non_Veg | E11: 4365 | G11: 4th sector | H11: 1537 | J11: Impact of delivery distance on On-time performance
A12: What is the percentage of deliveries completed under rainy conditions? | D12: Veg | E12: 1954 | G12: 5th Block | H12: 369
D13: 45200 | E13: 1958 | G13: 5th Block Kormangala | H13: 356 | J13: Count of on_time | K13: Column Labels
A14: Total Delivered orders | B14: orders delivered during rain | C14: % | D14: Non_Veg | E14: 1248 | G14: 5th Main Rd | H14: 455 | J14: Row Labels | K14: FALSE | L14: TRUE
A15: =COUNTA(Table2[order_status],"Delivered") -> 108 | B15: =COUNTIFS(Table2[order_status],"Delivered",Table2[rain_mode],2) -> 3 | C15: =B15/A15 -> 0.027777778 | D15: Veg | E15: 710 | G15: 5th sector | H15: 221 | J15: 0-2 Km | K15: 0.41176471 | L15: 0.58823529
D16: 45231 | E16: 2402 | G16: 7th Sector | H16: 1523 | J16: 2-5 Km | K16: 0.69565217 | L16: 0.30434783
D17: Non_Veg | E17: 1567 | G17: Bellandur Sarjapur | H17: 342 | J17: 5-8 Km | K17: 0.8 | L17: 0.2
D18: Veg | E18: 835 | G18: Devarabisanahalli | H18: 504
D19: 45261 | E19: 2678 | G19: Doddakanneli Village | H19: 287 | M19: Coupon Discount Distribution Analysis
A20: Most used Payment method | D20: Non_Veg | E20: 2211 | G20: Green Glen Layout | H20: 946
D21: Veg | E21: 467 | G21: Hosur Main Road | H21: 1315 | M21: Row Labels | N21: Sum of Discount _amount
A22: Row Labels | B22: Count of order_id | G22: HSR Layout | H22: 770 | M22: WORLDCUPMANIA | N22: 599.98 | P22: No coupon | Q22: 0
A23: UPIIntent | B23: 20 | G23: Indiranagar | H23: 356 | M23: TRYNEW | N23: 481.28 | P23: KINGK50 | Q23: 50.01
A24: UPICollect | B24: 25 | G24: Kaikondrahalli | H24: 853 | M24: PARTY | N24: 335 | P24: TRYNEW-XL | Q24: 62.09
G25: MANGAMMANAPALYA | H25: 1676 | M25: SWIGGYIT | N25: 300 | P25: SPECIALS | Q25: 80
G26: Outer Ring Road | H26: 265 | M26: JUMBO | N26: 228.99 | P26: LUNCHBINGE | Q26: 99.99
G27: Sarjapur - Marathahalli Rd | H27: 171 | M27: CELEBRATIONS | N27: 174.99 | P27: FLATDEAL | Q27: 100
A28: =SUM(Table2[net_total]) -> 43964 | G28: Sector 2 | H28: 530 | M28: MISSEDYOU | N28: 160 | P28: WEEKENDS | Q28: 125
A29: =AVERAGE(Table2[net_total]) -> 410.8785 | M29: WEEKENDS | N29: 125 | P29: MISSEDYOU | Q29: 160
M30: FLATDEAL | N30: 100 | P30: CELEBRATIONS | Q30: 174.99
A31: UPICollect | B31: 81 | M31: LUNCHBINGE | N31: 99.99 | P31: JUMBO | Q31: 228.99
A32: UPIIntent | B32: 20 | M32: SPECIALS | N32: 80 | P32: SWIGGYIT | Q32: 300
A33: Cash | B33: 6 | J33: Row Labels | K33: Sum of net_total | M33: TRYNEW-XL | N33: 62.09 | P33: PARTY | Q33: 335
J34: 12" Badmash Pizza | K34: 1369 | M34: KINGK50 | N34: 50.01 | P34: TRYNEW | Q34: 481.28
J35: Aloo Cheese Paratha | K35: 553 | M35: No coupon | N35: 0 | P35: WORLDCUPMANIA | Q35: 599.98
J36: Americano Pasta Non-veg | K36: 171
J37: Belgian Chocolate Milk Shake | K37: 369
J38: Belgian Chocolate Thick Shake | K38: 401
J39: Boneless Chicken Manchurian | K39: 530
J40: Cheese Ramyun | K40: 333
J41: Chicken Darjeeling Steam Momo | K41: 221
J42: Chicken Varattiyathu | K42: 573
J43: Chocolate And Love Smoothie Bowl | K43: 399
J44: Dark Chocolate Cake [350 Grams, Serves 3] | K44: 1136
J45: Dosa (2 Pcs) Chicken Curry | K45: 381
J46: Firecracker Wings | K46: 1905
J47: Garlic Mayo | K47: 221
... J71: Veg. Ramyun | K71: 826

Sheet Dashboard
